[
  {
    "COD_LOCALIDAD": 20270,
    "COD_POSTAL_VIEJO": 9051,
    "NOM_LOCALIDAD": "AGUADA A PIQUE",
    "COD_IDENT_PROV": "Z",
    "FE_ALTA": "2000-04-15T00:00:00",
    "COD_ESTADO": "A",
    "FE_ULT_ACT": "2000-04-15T00:00:00"
  },
  {
    "COD_LOCALIDAD": 20271,
    "COD_POSTAL_VIEJO": 9310,
    "NOM_LOCALIDAD": "AGUADA ALEGRE",
    "COD_IDENT_PROV": "Z",
    "FE_ALTA": "2000-04-15T00:00:00",
    "COD_ESTADO": "A",
    "FE_ULT_ACT": "2000-04-15T00:00:00"
  },
  {
    "COD_LOCALIDAD": 20272,
    "COD_POSTAL_VIEJO": 9018,
    "NOM_LOCALIDAD": "AGUADA ESCONDIDA",
    "COD_IDENT_PROV": "Z",
    "FE_ALTA": "2004-02-15T01:39:32.302816",
    "COD_ESTADO": "A",
    "FE_ULT_ACT": "2004-02-15T01:39:32.302816"
  },
  {
    "COD_LOCALIDAD": 20272,
    "COD_POSTAL_VIEJO": 9019,
    "NOM_LOCALIDAD": "AGUADA ESCONDIDA",
    "COD_IDENT_PROV": "Z",
    "FE_ALTA": "2000-04-15T00:00:00",
    "COD_ESTADO": "A",
    "FE_ULT_ACT": "2000-04-15T00:00:00"
  },
  {
    "COD_LOCALIDAD": 20273,
    "COD_POSTAL_VIEJO": 9053,
    "NOM_LOCALIDAD": "AGUADA GRANDE",
    "COD_IDENT_PROV": "Z",
    "FE_ALTA": "2000-04-15T00:00:00",
    "COD_ESTADO": "A",
    "FE_ULT_ACT": "2000-04-15T00:00:00"
  },
  {
    "COD_LOCALIDAD": 20274,
    "COD_POSTAL_VIEJO": 9051,
    "NOM_LOCALIDAD": "AGUADA LA OVEJA",
    "COD_IDENT_PROV": "Z",
    "FE_ALTA": "2000-04-15T00:00:00",
    "COD_ESTADO": "A",
    "FE_ULT_ACT": "2000-04-15T00:00:00"
  },
  {
    "COD_LOCALIDAD": 20275,
    "COD_POSTAL_VIEJO": 9015,
    "NOM_LOCALIDAD": "ALMA GRANDE",
    "COD_IDENT_PROV": "Z",
    "FE_ALTA": "2000-04-15T00:00:00",
    "COD_ESTADO": "A",
    "FE_ULT_ACT": "2000-04-15T00:00:00"
  },
  {
    "COD_LOCALIDAD": 20276,
    "COD_POSTAL_VIEJO": 9400,
    "NOM_LOCALIDAD": "AN AIKE",
    "COD_IDENT_PROV": "Z",
    "FE_ALTA": "2000-04-15T00:00:00",
    "COD_ESTADO": "A",
    "FE_ULT_ACT": "2000-04-15T00:00:00"
  },
  {
    "COD_LOCALIDAD": 20276,
    "COD_POSTAL_VIEJO": 9402,
    "NOM_LOCALIDAD": "AN AIKE",
    "COD_IDENT_PROV": "Z",
    "FE_ALTA": "2004-02-15T01:39:32.302816",
    "COD_ESTADO": "A",
    "FE_ULT_ACT": "2004-02-15T01:39:32.302816"
  },
  {
    "COD_LOCALIDAD": 20276,
    "COD_POSTAL_VIEJO": 9403,
    "NOM_LOCALIDAD": "AN AIKE",
    "COD_IDENT_PROV": "Z",
    "FE_ALTA": "2004-02-15T01:39:32.302816",
    "COD_ESTADO": "A",
    "FE_ULT_ACT": "2004-02-15T01:39:32.302816"
  },
  {
    "COD_LOCALIDAD": 20277,
    "COD_POSTAL_VIEJO": 9011,
    "NOM_LOCALIDAD": "BAHIA LANGARA",
    "COD_IDENT_PROV": "Z",
    "FE_ALTA": "2000-04-15T00:00:00",
    "COD_ESTADO": "A",
    "FE_ULT_ACT": "2000-04-15T00:00:00"
  },
  {
    "COD_LOCALIDAD": 20278,
    "COD_POSTAL_VIEJO": 9310,
    "NOM_LOCALIDAD": "BAHIA LAURA",
    "COD_IDENT_PROV": "Z",
    "FE_ALTA": "2000-04-15T00:00:00",
    "COD_ESTADO": "A",
    "FE_ULT_ACT": "2000-04-15T00:00:00"
  },
  {
    "COD_LOCALIDAD": 20279,
    "COD_POSTAL_VIEJO": 9404,
    "NOM_LOCALIDAD": "BAHIA TRANQUILA",
    "COD_IDENT_PROV": "Z",
    "FE_ALTA": "2004-02-15T01:39:32.302816",
    "COD_ESTADO": "A",
    "FE_ULT_ACT": "2004-02-15T01:39:32.302816"
  },
  {
    "COD_LOCALIDAD": 20279,
    "COD_POSTAL_VIEJO": 9405,
    "NOM_LOCALIDAD": "BAHIA TRANQUILA",
    "COD_IDENT_PROV": "Z",
    "FE_ALTA": "2000-04-15T00:00:00",
    "COD_ESTADO": "A",
    "FE_ULT_ACT": "2000-04-15T00:00:00"
  },
  {
    "COD_LOCALIDAD": 20280,
    "COD_POSTAL_VIEJO": 9315,
    "NOM_LOCALIDAD": "BAJO CARACOLES",
    "COD_IDENT_PROV": "Z",
    "FE_ALTA": "2000-04-15T00:00:00",
    "COD_ESTADO": "A",
    "FE_ULT_ACT": "2000-04-15T00:00:00"
  },
  {
    "COD_LOCALIDAD": 20281,
    "COD_POSTAL_VIEJO": 9310,
    "NOM_LOCALIDAD": "BAJO FUEGO",
    "COD_IDENT_PROV": "Z",
    "FE_ALTA": "2000-04-15T00:00:00",
    "COD_ESTADO": "A",
    "FE_ULT_ACT": "2000-04-15T00:00:00"
  },
  {
    "COD_LOCALIDAD": 20282,
    "COD_POSTAL_VIEJO": 9401,
    "NOM_LOCALIDAD": "BELLA VISTA",
    "COD_IDENT_PROV": "Z",
    "FE_ALTA": "2000-04-15T00:00:00",
    "COD_ESTADO": "A",
    "FE_ULT_ACT": "2000-04-15T00:00:00"
  },
  {
    "COD_LOCALIDAD": 20283,
    "COD_POSTAL_VIEJO": 9051,
    "NOM_LOCALIDAD": "CABO BLANCO",
    "COD_IDENT_PROV": "Z",
    "FE_ALTA": "2000-04-15T00:00:00",
    "COD_ESTADO": "A",
    "FE_ULT_ACT": "2000-04-15T00:00:00"
  },
  {
    "COD_LOCALIDAD": 20284,
    "COD_POSTAL_VIEJO": 9400,
    "NOM_LOCALIDAD": "CABO DE LAS VIRGENES",
    "COD_IDENT_PROV": "Z",
    "FE_ALTA": "2000-04-15T00:00:00",
    "COD_ESTADO": "A",
    "FE_ULT_ACT": "2000-04-15T00:00:00"
  },
  {
    "COD_LOCALIDAD": 20284,
    "COD_POSTAL_VIEJO": 9402,
    "NOM_LOCALIDAD": "CABO DE LAS VIRGENES",
    "COD_IDENT_PROV": "Z",
    "FE_ALTA": "2004-02-15T01:39:32.302816",
    "COD_ESTADO": "A",
    "FE_ULT_ACT": "2004-02-15T01:39:32.302816"
  },
  {
    "COD_LOCALIDAD": 20284,
    "COD_POSTAL_VIEJO": 9403,
    "NOM_LOCALIDAD": "CABO DE LAS VIRGENES",
    "COD_IDENT_PROV": "Z",
    "FE_ALTA": "2004-02-15T01:39:32.302816",
    "COD_ESTADO": "A",
    "FE_ULT_ACT": "2004-02-15T01:39:32.302816"
  },
  {
    "COD_LOCALIDAD": 20285,
    "COD_POSTAL_VIEJO": 9051,
    "NOM_LOCALIDAD": "CABO TRES PUNTAS",
    "COD_IDENT_PROV": "Z",
    "FE_ALTA": "2000-04-15T00:00:00",
    "COD_ESTADO": "A",
    "FE_ULT_ACT": "2000-04-15T00:00:00"
  },
  {
    "COD_LOCALIDAD": 20286,
    "COD_POSTAL_VIEJO": 9011,
    "NOM_LOCALIDAD": "CALETA OLIVIA",
    "COD_IDENT_PROV": "Z",
    "FE_ALTA": "2000-04-15T00:00:00",
    "COD_ESTADO": "A",
    "FE_ULT_ACT": "2000-04-15T00:00:00"
  },
  {
    "COD_LOCALIDAD": 20287,
    "COD_POSTAL_VIEJO": 9017,
    "NOM_LOCALIDAD": "CAMERON",
    "COD_IDENT_PROV": "Z",
    "FE_ALTA": "2000-04-15T00:00:00",
    "COD_ESTADO": "A",
    "FE_ULT_ACT": "2000-04-15T00:00:00"
  },
  {
    "COD_LOCALIDAD": 20288,
    "COD_POSTAL_VIEJO": 9398,
    "NOM_LOCALIDAD": "CAMPAMENTO DOROTEA",
    "COD_IDENT_PROV": "Z",
    "FE_ALTA": "2004-02-15T01:39:32.302816",
    "COD_ESTADO": "A",
    "FE_ULT_ACT": "2004-02-15T01:39:32.302816"
  },
  {
    "COD_LOCALIDAD": 20288,
    "COD_POSTAL_VIEJO": 9407,
    "NOM_LOCALIDAD": "CAMPAMENTO DOROTEA",
    "COD_IDENT_PROV": "Z",
    "FE_ALTA": "2000-04-15T00:00:00",
    "COD_ESTADO": "A",
    "FE_ULT_ACT": "2000-04-15T00:00:00"
  },
  {
    "COD_LOCALIDAD": 20288,
    "COD_POSTAL_VIEJO": 9408,
    "NOM_LOCALIDAD": "CAMPAMENTO DOROTEA",
    "COD_IDENT_PROV": "Z",
    "FE_ALTA": "2004-02-15T01:39:32.302816",
    "COD_ESTADO": "A",
    "FE_ULT_ACT": "2004-02-15T01:39:32.302816"
  },
  {
    "COD_LOCALIDAD": 20289,
    "COD_POSTAL_VIEJO": 9400,
    "NOM_LOCALIDAD": "CAMUZU AIKE",
    "COD_IDENT_PROV": "Z",
    "FE_ALTA": "2000-04-15T00:00:00",
    "COD_ESTADO": "A",
    "FE_ULT_ACT": "2000-04-15T00:00:00"
  },
  {
    "COD_LOCALIDAD": 20289,
    "COD_POSTAL_VIEJO": 9402,
    "NOM_LOCALIDAD": "CAMUZU AIKE",
    "COD_IDENT_PROV": "Z",
    "FE_ALTA": "2004-02-15T01:39:32.302816",
    "COD_ESTADO": "A",
    "FE_ULT_ACT": "2004-02-15T01:39:32.302816"
  },
  {
    "COD_LOCALIDAD": 20289,
    "COD_POSTAL_VIEJO": 9403,
    "NOM_LOCALIDAD": "CAMUZU AIKE",
    "COD_IDENT_PROV": "Z",
    "FE_ALTA": "2004-02-15T01:39:32.302816",
    "COD_ESTADO": "A",
    "FE_ULT_ACT": "2004-02-15T01:39:32.302816"
  },
  {
    "COD_LOCALIDAD": 20290,
    "COD_POSTAL_VIEJO": 9400,
    "NOM_LOCALIDAD": "CANCHA CARRERA",
    "COD_IDENT_PROV": "Z",
    "FE_ALTA": "2000-04-15T00:00:00",
    "COD_ESTADO": "A",
    "FE_ULT_ACT": "2000-04-15T00:00:00"
  },
  {
    "COD_LOCALIDAD": 20290,
    "COD_POSTAL_VIEJO": 9402,
    "NOM_LOCALIDAD": "CANCHA CARRERA",
    "COD_IDENT_PROV": "Z",
    "FE_ALTA": "2004-02-15T01:39:32.302816",
    "COD_ESTADO": "A",
    "FE_ULT_ACT": "2004-02-15T01:39:32.302816"
  },
  {
    "COD_LOCALIDAD": 20290,
    "COD_POSTAL_VIEJO": 9403,
    "NOM_LOCALIDAD": "CANCHA CARRERA",
    "COD_IDENT_PROV": "Z",
    "FE_ALTA": "2004-02-15T01:39:32.302816",
    "COD_ESTADO": "A",
    "FE_ULT_ACT": "2004-02-15T01:39:32.302816"
  },
  {
    "COD_LOCALIDAD": 20291,
    "COD_POSTAL_VIEJO": 9400,
    "NOM_LOCALIDAD": "CAP",
    "COD_IDENT_PROV": "Z",
    "FE_ALTA": "2000-04-15T00:00:00",
    "COD_ESTADO": "A",
    "FE_ULT_ACT": "2000-04-15T00:00:00"
  },
  {
    "COD_LOCALIDAD": 20291,
    "COD_POSTAL_VIEJO": 9402,
    "NOM_LOCALIDAD": "CAP",
    "COD_IDENT_PROV": "Z",
    "FE_ALTA": "2004-02-15T01:39:32.302816",
    "COD_ESTADO": "A",
    "FE_ULT_ACT": "2004-02-15T01:39:32.302816"
  },
  {
    "COD_LOCALIDAD": 20291,
    "COD_POSTAL_VIEJO": 9403,
    "NOM_LOCALIDAD": "CAP",
    "COD_IDENT_PROV": "Z",
    "FE_ALTA": "2004-02-15T01:39:32.302816",
    "COD_ESTADO": "A",
    "FE_ULT_ACT": "2004-02-15T01:39:32.302816"
  },
  {
    "COD_LOCALIDAD": 20292,
    "COD_POSTAL_VIEJO": 9313,
    "NOM_LOCALIDAD": "CARA MALA",
    "COD_IDENT_PROV": "Z",
    "FE_ALTA": "2000-04-15T00:00:00",
    "COD_ESTADO": "A",
    "FE_ULT_ACT": "2000-04-15T00:00:00"
  },
  {
    "COD_LOCALIDAD": 20293,
    "COD_POSTAL_VIEJO": 9305,
    "NOM_LOCALIDAD": "CAÑADA DE LAS VACAS",
    "COD_IDENT_PROV": "Z",
    "FE_ALTA": "2000-04-15T00:00:00",
    "COD_ESTADO": "A",
    "FE_ULT_ACT": "2000-04-15T00:00:00"
  },
  {
    "COD_LOCALIDAD": 20294,
    "COD_POSTAL_VIEJO": 9040,
    "NOM_LOCALIDAD": "CAÑADON BOTELLO",
    "COD_IDENT_PROV": "Z",
    "FE_ALTA": "2000-04-15T00:00:00",
    "COD_ESTADO": "A",
    "FE_ULT_ACT": "2000-04-15T00:00:00"
  },
  {
    "COD_LOCALIDAD": 20295,
    "COD_POSTAL_VIEJO": 9300,
    "NOM_LOCALIDAD": "CAÑADON DE LAS VACAS",
    "COD_IDENT_PROV": "Z",
    "FE_ALTA": "2000-04-15T00:00:00",
    "COD_ESTADO": "A",
    "FE_ULT_ACT": "2000-04-15T00:00:00"
  },
  {
    "COD_LOCALIDAD": 20296,
    "COD_POSTAL_VIEJO": 9300,
    "NOM_LOCALIDAD": "CAÑADON DEL RANCHO",
    "COD_IDENT_PROV": "Z",
    "FE_ALTA": "2000-04-15T00:00:00",
    "COD_ESTADO": "A",
    "FE_ULT_ACT": "2000-04-15T00:00:00"
  },
  {
    "COD_LOCALIDAD": 20297,
    "COD_POSTAL_VIEJO": 9303,
    "NOM_LOCALIDAD": "CAÑADON DEL TORO",
    "COD_IDENT_PROV": "Z",
    "FE_ALTA": "2000-04-15T00:00:00",
    "COD_ESTADO": "A",
    "FE_ULT_ACT": "2000-04-15T00:00:00"
  },
  {
    "COD_LOCALIDAD": 20298,
    "COD_POSTAL_VIEJO": 9400,
    "NOM_LOCALIDAD": "CAÑADON FABRE",
    "COD_IDENT_PROV": "Z",
    "FE_ALTA": "2000-04-15T00:00:00",
    "COD_ESTADO": "A",
    "FE_ULT_ACT": "2000-04-15T00:00:00"
  },
  {
    "COD_LOCALIDAD": 20298,
    "COD_POSTAL_VIEJO": 9402,
    "NOM_LOCALIDAD": "CAÑADON FABRE",
    "COD_IDENT_PROV": "Z",
    "FE_ALTA": "2004-02-15T01:39:32.302816",
    "COD_ESTADO": "A",
    "FE_ULT_ACT": "2004-02-15T01:39:32.302816"
  },
  {
    "COD_LOCALIDAD": 20298,
    "COD_POSTAL_VIEJO": 9403,
    "NOM_LOCALIDAD": "CAÑADON FABRE",
    "COD_IDENT_PROV": "Z",
    "FE_ALTA": "2004-02-15T01:39:32.302816",
    "COD_ESTADO": "A",
    "FE_ULT_ACT": "2004-02-15T01:39:32.302816"
  },
  {
    "COD_LOCALIDAD": 20299,
    "COD_POSTAL_VIEJO": 9311,
    "NOM_LOCALIDAD": "CAÑADON LEON",
    "COD_IDENT_PROV": "Z",
    "FE_ALTA": "2000-04-15T00:00:00",
    "COD_ESTADO": "A",
    "FE_ULT_ACT": "2000-04-15T00:00:00"
  },
  {
    "COD_LOCALIDAD": 20300,
    "COD_POSTAL_VIEJO": 9311,
    "NOM_LOCALIDAD": "CAÑADON MOLINARI",
    "COD_IDENT_PROV": "Z",
    "FE_ALTA": "2000-04-15T00:00:00",
    "COD_ESTADO": "A",
    "FE_ULT_ACT": "2000-04-15T00:00:00"
  },
  {
    "COD_LOCALIDAD": 20301,
    "COD_POSTAL_VIEJO": 9017,
    "NOM_LOCALIDAD": "CAÑADON PLUMA",
    "COD_IDENT_PROV": "Z",
    "FE_ALTA": "2000-04-15T00:00:00",
    "COD_ESTADO": "A",
    "FE_ULT_ACT": "2000-04-15T00:00:00"
  },
  {
    "COD_LOCALIDAD": 20302,
    "COD_POSTAL_VIEJO": 9013,
    "NOM_LOCALIDAD": "CAÑADON SECO",
    "COD_IDENT_PROV": "Z",
    "FE_ALTA": "2000-04-15T00:00:00",
    "COD_ESTADO": "A",
    "FE_ULT_ACT": "2000-04-15T00:00:00"
  },
  {
    "COD_LOCALIDAD": 20303,
    "COD_POSTAL_VIEJO": 9310,
    "NOM_LOCALIDAD": "CAÑADON 11 DE SETIEMBRE",
    "COD_IDENT_PROV": "Z",
    "FE_ALTA": "2000-04-15T00:00:00",
    "COD_ESTADO": "A",
    "FE_ULT_ACT": "2000-04-15T00:00:00"
  },
  {
    "COD_LOCALIDAD": 20304,
    "COD_POSTAL_VIEJO": 9053,
    "NOM_LOCALIDAD": "CERRO ALTO",
    "COD_IDENT_PROV": "Z",
    "FE_ALTA": "2000-04-15T00:00:00",
    "COD_ESTADO": "A",
    "FE_ULT_ACT": "2000-04-15T00:00:00"
  },
  {
    "COD_LOCALIDAD": 20305,
    "COD_POSTAL_VIEJO": 9017,
    "NOM_LOCALIDAD": "CERRO LA SETENTA",
    "COD_IDENT_PROV": "Z",
    "FE_ALTA": "2000-04-15T00:00:00",
    "COD_ESTADO": "A",
    "FE_ULT_ACT": "2000-04-15T00:00:00"
  },
  {
    "COD_LOCALIDAD": 20306,
    "COD_POSTAL_VIEJO": 9011,
    "NOM_LOCALIDAD": "CERRO MANGRULLO",
    "COD_IDENT_PROV": "Z",
    "FE_ALTA": "2000-04-15T00:00:00",
    "COD_ESTADO": "A",
    "FE_ULT_ACT": "2000-04-15T00:00:00"
  },
  {
    "COD_LOCALIDAD": 20307,
    "COD_POSTAL_VIEJO": 9018,
    "NOM_LOCALIDAD": "CERRO MORO",
    "COD_IDENT_PROV": "Z",
    "FE_ALTA": "2004-02-15T01:39:32.302816",
    "COD_ESTADO": "A",
    "FE_ULT_ACT": "2004-02-15T01:39:32.302816"
  },
  {
    "COD_LOCALIDAD": 20307,
    "COD_POSTAL_VIEJO": 9019,
    "NOM_LOCALIDAD": "CERRO MORO",
    "COD_IDENT_PROV": "Z",
    "FE_ALTA": "2000-04-15T00:00:00",
    "COD_ESTADO": "A",
    "FE_ULT_ACT": "2000-04-15T00:00:00"
  },
  {
    "COD_LOCALIDAD": 20308,
    "COD_POSTAL_VIEJO": 9053,
    "NOM_LOCALIDAD": "CERRO NEGRO",
    "COD_IDENT_PROV": "Z",
    "FE_ALTA": "2000-04-15T00:00:00",
    "COD_ESTADO": "A",
    "FE_ULT_ACT": "2000-04-15T00:00:00"
  },
  {
    "COD_LOCALIDAD": 20309,
    "COD_POSTAL_VIEJO": 9400,
    "NOM_LOCALIDAD": "CERRO PALIQUE",
    "COD_IDENT_PROV": "Z",
    "FE_ALTA": "2000-04-15T00:00:00",
    "COD_ESTADO": "A",
    "FE_ULT_ACT": "2000-04-15T00:00:00"
  },
  {
    "COD_LOCALIDAD": 20309,
    "COD_POSTAL_VIEJO": 9402,
    "NOM_LOCALIDAD": "CERRO PALIQUE",
    "COD_IDENT_PROV": "Z",
    "FE_ALTA": "2004-02-15T01:39:32.302816",
    "COD_ESTADO": "A",
    "FE_ULT_ACT": "2004-02-15T01:39:32.302816"
  },
  {
    "COD_LOCALIDAD": 20309,
    "COD_POSTAL_VIEJO": 9403,
    "NOM_LOCALIDAD": "CERRO PALIQUE",
    "COD_IDENT_PROV": "Z",
    "FE_ALTA": "2004-02-15T01:39:32.302816",
    "COD_ESTADO": "A",
    "FE_ULT_ACT": "2004-02-15T01:39:32.302816"
  },
  {
    "COD_LOCALIDAD": 20310,
    "COD_POSTAL_VIEJO": 9051,
    "NOM_LOCALIDAD": "CERRO PUNTUDO",
    "COD_IDENT_PROV": "Z",
    "FE_ALTA": "2000-04-15T00:00:00",
    "COD_ESTADO": "A",
    "FE_ULT_ACT": "2000-04-15T00:00:00"
  },
  {
    "COD_LOCALIDAD": 20311,
    "COD_POSTAL_VIEJO": 9051,
    "NOM_LOCALIDAD": "CERRO REDONDO",
    "COD_IDENT_PROV": "Z",
    "FE_ALTA": "2000-04-15T00:00:00",
    "COD_ESTADO": "A",
    "FE_ULT_ACT": "2000-04-15T00:00:00"
  },
  {
    "COD_LOCALIDAD": 20311,
    "COD_POSTAL_VIEJO": 9303,
    "NOM_LOCALIDAD": "CERRO REDONDO",
    "COD_IDENT_PROV": "Z",
    "FE_ALTA": "2000-04-15T00:00:00",
    "COD_ESTADO": "A",
    "FE_ULT_ACT": "2000-04-15T00:00:00"
  },
  {
    "COD_LOCALIDAD": 20312,
    "COD_POSTAL_VIEJO": 9017,
    "NOM_LOCALIDAD": "CERRO RENZEL",
    "COD_IDENT_PROV": "Z",
    "FE_ALTA": "2000-04-15T00:00:00",
    "COD_ESTADO": "A",
    "FE_ULT_ACT": "2000-04-15T00:00:00"
  },
  {
    "COD_LOCALIDAD": 20313,
    "COD_POSTAL_VIEJO": 9017,
    "NOM_LOCALIDAD": "CERRO SILVA",
    "COD_IDENT_PROV": "Z",
    "FE_ALTA": "2000-04-15T00:00:00",
    "COD_ESTADO": "A",
    "FE_ULT_ACT": "2000-04-15T00:00:00"
  },
  {
    "COD_LOCALIDAD": 20314,
    "COD_POSTAL_VIEJO": 9400,
    "NOM_LOCALIDAD": "CHALL AIKE",
    "COD_IDENT_PROV": "Z",
    "FE_ALTA": "2000-04-15T00:00:00",
    "COD_ESTADO": "A",
    "FE_ULT_ACT": "2000-04-15T00:00:00"
  },
  {
    "COD_LOCALIDAD": 20314,
    "COD_POSTAL_VIEJO": 9402,
    "NOM_LOCALIDAD": "CHALL AIKE",
    "COD_IDENT_PROV": "Z",
    "FE_ALTA": "2004-02-15T01:39:32.302816",
    "COD_ESTADO": "A",
    "FE_ULT_ACT": "2004-02-15T01:39:32.302816"
  },
  {
    "COD_LOCALIDAD": 20314,
    "COD_POSTAL_VIEJO": 9403,
    "NOM_LOCALIDAD": "CHALL AIKE",
    "COD_IDENT_PROV": "Z",
    "FE_ALTA": "2004-02-15T01:39:32.302816",
    "COD_ESTADO": "A",
    "FE_ULT_ACT": "2004-02-15T01:39:32.302816"
  },
  {
    "COD_LOCALIDAD": 20315,
    "COD_POSTAL_VIEJO": 9303,
    "NOM_LOCALIDAD": "CHONQUE",
    "COD_IDENT_PROV": "Z",
    "FE_ALTA": "2000-04-15T00:00:00",
    "COD_ESTADO": "A",
    "FE_ULT_ACT": "2000-04-15T00:00:00"
  },
  {
    "COD_LOCALIDAD": 20316,
    "COD_POSTAL_VIEJO": 9017,
    "NOM_LOCALIDAD": "COLONIA CARLOS PELLEGRINI",
    "COD_IDENT_PROV": "Z",
    "FE_ALTA": "2000-04-15T00:00:00",
    "COD_ESTADO": "A",
    "FE_ULT_ACT": "2000-04-15T00:00:00"
  },
  {
    "COD_LOCALIDAD": 20317,
    "COD_POSTAL_VIEJO": 9040,
    "NOM_LOCALIDAD": "COLONIA LEANDRO N ALEM",
    "COD_IDENT_PROV": "Z",
    "FE_ALTA": "2000-04-15T00:00:00",
    "COD_ESTADO": "A",
    "FE_ULT_ACT": "2000-04-15T00:00:00"
  },
  {
    "COD_LOCALIDAD": 20318,
    "COD_POSTAL_VIEJO": 9303,
    "NOM_LOCALIDAD": "COMANDANTE LUIS PIEDRABUENA",
    "COD_IDENT_PROV": "Z",
    "FE_ALTA": "2000-04-15T00:00:00",
    "COD_ESTADO": "A",
    "FE_ULT_ACT": "2000-04-15T00:00:00"
  },
  {
    "COD_LOCALIDAD": 20319,
    "COD_POSTAL_VIEJO": 9400,
    "NOM_LOCALIDAD": "CONDOR",
    "COD_IDENT_PROV": "Z",
    "FE_ALTA": "2000-04-15T00:00:00",
    "COD_ESTADO": "A",
    "FE_ULT_ACT": "2000-04-15T00:00:00"
  },
  {
    "COD_LOCALIDAD": 20319,
    "COD_POSTAL_VIEJO": 9402,
    "NOM_LOCALIDAD": "CONDOR",
    "COD_IDENT_PROV": "Z",
    "FE_ALTA": "2004-02-15T01:39:32.302816",
    "COD_ESTADO": "A",
    "FE_ULT_ACT": "2004-02-15T01:39:32.302816"
  },
  {
    "COD_LOCALIDAD": 20319,
    "COD_POSTAL_VIEJO": 9403,
    "NOM_LOCALIDAD": "CONDOR",
    "COD_IDENT_PROV": "Z",
    "FE_ALTA": "2004-02-15T01:39:32.302816",
    "COD_ESTADO": "A",
    "FE_ULT_ACT": "2004-02-15T01:39:32.302816"
  },
  {
    "COD_LOCALIDAD": 20320,
    "COD_POSTAL_VIEJO": 9404,
    "NOM_LOCALIDAD": "CONDOR CLIF",
    "COD_IDENT_PROV": "Z",
    "FE_ALTA": "2004-02-15T01:39:32.302816",
    "COD_ESTADO": "A",
    "FE_ULT_ACT": "2004-02-15T01:39:32.302816"
  },
  {
    "COD_LOCALIDAD": 20320,
    "COD_POSTAL_VIEJO": 9405,
    "NOM_LOCALIDAD": "CONDOR CLIF",
    "COD_IDENT_PROV": "Z",
    "FE_ALTA": "2000-04-15T00:00:00",
    "COD_ESTADO": "A",
    "FE_ULT_ACT": "2000-04-15T00:00:00"
  },
  {
    "COD_LOCALIDAD": 20321,
    "COD_POSTAL_VIEJO": 9400,
    "NOM_LOCALIDAD": "CORONEL GUARUMBA",
    "COD_IDENT_PROV": "Z",
    "FE_ALTA": "2000-04-15T00:00:00",
    "COD_ESTADO": "A",
    "FE_ULT_ACT": "2000-04-15T00:00:00"
  },
  {
    "COD_LOCALIDAD": 20321,
    "COD_POSTAL_VIEJO": 9402,
    "NOM_LOCALIDAD": "CORONEL GUARUMBA",
    "COD_IDENT_PROV": "Z",
    "FE_ALTA": "2004-02-15T01:39:32.302816",
    "COD_ESTADO": "A",
    "FE_ULT_ACT": "2004-02-15T01:39:32.302816"
  },
  {
    "COD_LOCALIDAD": 20321,
    "COD_POSTAL_VIEJO": 9403,
    "NOM_LOCALIDAD": "CORONEL GUARUMBA",
    "COD_IDENT_PROV": "Z",
    "FE_ALTA": "2004-02-15T01:39:32.302816",
    "COD_ESTADO": "A",
    "FE_ULT_ACT": "2004-02-15T01:39:32.302816"
  },
  {
    "COD_LOCALIDAD": 20322,
    "COD_POSTAL_VIEJO": 9398,
    "NOM_LOCALIDAD": "CORONEL MARTIN IRIGOYEN",
    "COD_IDENT_PROV": "Z",
    "FE_ALTA": "2004-02-15T01:39:32.302816",
    "COD_ESTADO": "A",
    "FE_ULT_ACT": "2004-02-15T01:39:32.302816"
  },
  {
    "COD_LOCALIDAD": 20322,
    "COD_POSTAL_VIEJO": 9407,
    "NOM_LOCALIDAD": "CORONEL MARTIN IRIGOYEN",
    "COD_IDENT_PROV": "Z",
    "FE_ALTA": "2000-04-15T00:00:00",
    "COD_ESTADO": "A",
    "FE_ULT_ACT": "2000-04-15T00:00:00"
  },
  {
    "COD_LOCALIDAD": 20322,
    "COD_POSTAL_VIEJO": 9408,
    "NOM_LOCALIDAD": "CORONEL MARTIN IRIGOYEN",
    "COD_IDENT_PROV": "Z",
    "FE_ALTA": "2004-02-15T01:39:32.302816",
    "COD_ESTADO": "A",
    "FE_ULT_ACT": "2004-02-15T01:39:32.302816"
  },
  {
    "COD_LOCALIDAD": 20323,
    "COD_POSTAL_VIEJO": 9017,
    "NOM_LOCALIDAD": "CUEVA DE LAS MANOS",
    "COD_IDENT_PROV": "Z",
    "FE_ALTA": "2000-04-15T00:00:00",
    "COD_ESTADO": "A",
    "FE_ULT_ACT": "2000-04-15T00:00:00"
  },
  {
    "COD_LOCALIDAD": 20324,
    "COD_POSTAL_VIEJO": 9053,
    "NOM_LOCALIDAD": "DESAMPARADOS",
    "COD_IDENT_PROV": "Z",
    "FE_ALTA": "2000-04-15T00:00:00",
    "COD_ESTADO": "A",
    "FE_ULT_ACT": "2000-04-15T00:00:00"
  },
  {
    "COD_LOCALIDAD": 20325,
    "COD_POSTAL_VIEJO": 9303,
    "NOM_LOCALIDAD": "EL BAILE",
    "COD_IDENT_PROV": "Z",
    "FE_ALTA": "2000-04-15T00:00:00",
    "COD_ESTADO": "A",
    "FE_ULT_ACT": "2000-04-15T00:00:00"
  },
  {
    "COD_LOCALIDAD": 20326,
    "COD_POSTAL_VIEJO": 9053,
    "NOM_LOCALIDAD": "EL BARBUCHO",
    "COD_IDENT_PROV": "Z",
    "FE_ALTA": "2000-04-15T00:00:00",
    "COD_ESTADO": "A",
    "FE_ULT_ACT": "2000-04-15T00:00:00"
  },
  {
    "COD_LOCALIDAD": 20327,
    "COD_POSTAL_VIEJO": 9404,
    "NOM_LOCALIDAD": "EL CALAFATE",
    "COD_IDENT_PROV": "Z",
    "FE_ALTA": "2004-02-15T01:39:32.302816",
    "COD_ESTADO": "A",
    "FE_ULT_ACT": "2004-02-15T01:39:32.302816"
  },
  {
    "COD_LOCALIDAD": 20327,
    "COD_POSTAL_VIEJO": 9405,
    "NOM_LOCALIDAD": "EL CALAFATE",
    "COD_IDENT_PROV": "Z",
    "FE_ALTA": "2000-04-15T00:00:00",
    "COD_ESTADO": "A",
    "FE_ULT_ACT": "2000-04-15T00:00:00"
  },
  {
    "COD_LOCALIDAD": 20328,
    "COD_POSTAL_VIEJO": 9404,
    "NOM_LOCALIDAD": "EL CERRITO",
    "COD_IDENT_PROV": "Z",
    "FE_ALTA": "2004-02-15T01:39:32.302816",
    "COD_ESTADO": "A",
    "FE_ULT_ACT": "2004-02-15T01:39:32.302816"
  },
  {
    "COD_LOCALIDAD": 20328,
    "COD_POSTAL_VIEJO": 9405,
    "NOM_LOCALIDAD": "EL CERRITO",
    "COD_IDENT_PROV": "Z",
    "FE_ALTA": "2000-04-15T00:00:00",
    "COD_ESTADO": "A",
    "FE_ULT_ACT": "2000-04-15T00:00:00"
  },
  {
    "COD_LOCALIDAD": 20329,
    "COD_POSTAL_VIEJO": 9301,
    "NOM_LOCALIDAD": "EL CHALTEN",
    "COD_IDENT_PROV": "Z",
    "FE_ALTA": "2000-04-15T00:00:00",
    "COD_ESTADO": "A",
    "FE_ULT_ACT": "2000-04-15T00:00:00"
  },
  {
    "COD_LOCALIDAD": 20330,
    "COD_POSTAL_VIEJO": 9051,
    "NOM_LOCALIDAD": "EL CHARA",
    "COD_IDENT_PROV": "Z",
    "FE_ALTA": "2000-04-15T00:00:00",
    "COD_ESTADO": "A",
    "FE_ULT_ACT": "2000-04-15T00:00:00"
  },
  {
    "COD_LOCALIDAD": 20331,
    "COD_POSTAL_VIEJO": 9300,
    "NOM_LOCALIDAD": "EL GUADAL",
    "COD_IDENT_PROV": "Z",
    "FE_ALTA": "2000-04-15T00:00:00",
    "COD_ESTADO": "A",
    "FE_ULT_ACT": "2000-04-15T00:00:00"
  },
  {
    "COD_LOCALIDAD": 20332,
    "COD_POSTAL_VIEJO": 9051,
    "NOM_LOCALIDAD": "EL HUECO",
    "COD_IDENT_PROV": "Z",
    "FE_ALTA": "2000-04-15T00:00:00",
    "COD_ESTADO": "A",
    "FE_ULT_ACT": "2000-04-15T00:00:00"
  },
  {
    "COD_LOCALIDAD": 20333,
    "COD_POSTAL_VIEJO": 9051,
    "NOM_LOCALIDAD": "EL LORO",
    "COD_IDENT_PROV": "Z",
    "FE_ALTA": "2000-04-15T00:00:00",
    "COD_ESTADO": "A",
    "FE_ULT_ACT": "2000-04-15T00:00:00"
  },
  {
    "COD_LOCALIDAD": 20334,
    "COD_POSTAL_VIEJO": 9303,
    "NOM_LOCALIDAD": "EL PAN DE AZUCAR",
    "COD_IDENT_PROV": "Z",
    "FE_ALTA": "2000-04-15T00:00:00",
    "COD_ESTADO": "A",
    "FE_ULT_ACT": "2000-04-15T00:00:00"
  },
  {
    "COD_LOCALIDAD": 20335,
    "COD_POSTAL_VIEJO": 9303,
    "NOM_LOCALIDAD": "EL PASO",
    "COD_IDENT_PROV": "Z",
    "FE_ALTA": "2000-04-15T00:00:00",
    "COD_ESTADO": "A",
    "FE_ULT_ACT": "2000-04-15T00:00:00"
  },
  {
    "COD_LOCALIDAD": 20336,
    "COD_POSTAL_VIEJO": 9017,
    "NOM_LOCALIDAD": "EL PLUMA",
    "COD_IDENT_PROV": "Z",
    "FE_ALTA": "2000-04-15T00:00:00",
    "COD_ESTADO": "A",
    "FE_ULT_ACT": "2000-04-15T00:00:00"
  },
  {
    "COD_LOCALIDAD": 20337,
    "COD_POSTAL_VIEJO": 9051,
    "NOM_LOCALIDAD": "EL POLVORIN",
    "COD_IDENT_PROV": "Z",
    "FE_ALTA": "2000-04-15T00:00:00",
    "COD_ESTADO": "A",
    "FE_ULT_ACT": "2000-04-15T00:00:00"
  },
  {
    "COD_LOCALIDAD": 20338,
    "COD_POSTAL_VIEJO": 9040,
    "NOM_LOCALIDAD": "EL PORTEZUELO",
    "COD_IDENT_PROV": "Z",
    "FE_ALTA": "2000-04-15T00:00:00",
    "COD_ESTADO": "A",
    "FE_ULT_ACT": "2000-04-15T00:00:00"
  },
  {
    "COD_LOCALIDAD": 20339,
    "COD_POSTAL_VIEJO": 9313,
    "NOM_LOCALIDAD": "EL SALADO",
    "COD_IDENT_PROV": "Z",
    "FE_ALTA": "2000-04-15T00:00:00",
    "COD_ESTADO": "A",
    "FE_ULT_ACT": "2000-04-15T00:00:00"
  },
  {
    "COD_LOCALIDAD": 20340,
    "COD_POSTAL_VIEJO": 9398,
    "NOM_LOCALIDAD": "EL TURBIO",
    "COD_IDENT_PROV": "Z",
    "FE_ALTA": "2004-02-15T01:39:32.302816",
    "COD_ESTADO": "A",
    "FE_ULT_ACT": "2004-02-15T01:39:32.302816"
  },
  {
    "COD_LOCALIDAD": 20340,
    "COD_POSTAL_VIEJO": 9407,
    "NOM_LOCALIDAD": "EL TURBIO",
    "COD_IDENT_PROV": "Z",
    "FE_ALTA": "2000-04-15T00:00:00",
    "COD_ESTADO": "A",
    "FE_ULT_ACT": "2000-04-15T00:00:00"
  },
  {
    "COD_LOCALIDAD": 20340,
    "COD_POSTAL_VIEJO": 9408,
    "NOM_LOCALIDAD": "EL TURBIO",
    "COD_IDENT_PROV": "Z",
    "FE_ALTA": "2004-02-15T01:39:32.302816",
    "COD_ESTADO": "A",
    "FE_ULT_ACT": "2004-02-15T01:39:32.302816"
  },
  {
    "COD_LOCALIDAD": 20341,
    "COD_POSTAL_VIEJO": 9401,
    "NOM_LOCALIDAD": "EL ZURDO",
    "COD_IDENT_PROV": "Z",
    "FE_ALTA": "2000-04-15T00:00:00",
    "COD_ESTADO": "A",
    "FE_ULT_ACT": "2000-04-15T00:00:00"
  },
  {
    "COD_LOCALIDAD": 20342,
    "COD_POSTAL_VIEJO": 9400,
    "NOM_LOCALIDAD": "ESTACION ING ATILIO CAPPA",
    "COD_IDENT_PROV": "Z",
    "FE_ALTA": "2000-04-15T00:00:00",
    "COD_ESTADO": "A",
    "FE_ULT_ACT": "2000-04-15T00:00:00"
  },
  {
    "COD_LOCALIDAD": 20342,
    "COD_POSTAL_VIEJO": 9402,
    "NOM_LOCALIDAD": "ESTACION ING ATILIO CAPPA",
    "COD_IDENT_PROV": "Z",
    "FE_ALTA": "2004-02-15T01:39:32.302816",
    "COD_ESTADO": "A",
    "FE_ULT_ACT": "2004-02-15T01:39:32.302816"
  },
  {
    "COD_LOCALIDAD": 20342,
    "COD_POSTAL_VIEJO": 9403,
    "NOM_LOCALIDAD": "ESTACION ING ATILIO CAPPA",
    "COD_IDENT_PROV": "Z",
    "FE_ALTA": "2004-02-15T01:39:32.302816",
    "COD_ESTADO": "A",
    "FE_ULT_ACT": "2004-02-15T01:39:32.302816"
  },
  {
    "COD_LOCALIDAD": 20343,
    "COD_POSTAL_VIEJO": 9313,
    "NOM_LOCALIDAD": "FARO CABO GUARDIAN",
    "COD_IDENT_PROV": "Z",
    "FE_ALTA": "2000-04-15T00:00:00",
    "COD_ESTADO": "A",
    "FE_ULT_ACT": "2000-04-15T00:00:00"
  },
  {
    "COD_LOCALIDAD": 20344,
    "COD_POSTAL_VIEJO": 9313,
    "NOM_LOCALIDAD": "FARO CAMPANA",
    "COD_IDENT_PROV": "Z",
    "FE_ALTA": "2000-04-15T00:00:00",
    "COD_ESTADO": "A",
    "FE_ULT_ACT": "2000-04-15T00:00:00"
  },
  {
    "COD_LOCALIDAD": 20345,
    "COD_POSTAL_VIEJO": 9018,
    "NOM_LOCALIDAD": "FITZ ROY",
    "COD_IDENT_PROV": "Z",
    "FE_ALTA": "2004-02-15T01:39:32.302816",
    "COD_ESTADO": "A",
    "FE_ULT_ACT": "2004-02-15T01:39:32.302816"
  },
  {
    "COD_LOCALIDAD": 20345,
    "COD_POSTAL_VIEJO": 9019,
    "NOM_LOCALIDAD": "FITZ ROY",
    "COD_IDENT_PROV": "Z",
    "FE_ALTA": "2000-04-15T00:00:00",
    "COD_ESTADO": "A",
    "FE_ULT_ACT": "2000-04-15T00:00:00"
  },
  {
    "COD_LOCALIDAD": 20346,
    "COD_POSTAL_VIEJO": 9053,
    "NOM_LOCALIDAD": "FLORADORA",
    "COD_IDENT_PROV": "Z",
    "FE_ALTA": "2000-04-15T00:00:00",
    "COD_ESTADO": "A",
    "FE_ULT_ACT": "2000-04-15T00:00:00"
  },
  {
    "COD_LOCALIDAD": 20347,
    "COD_POSTAL_VIEJO": 9401,
    "NOM_LOCALIDAD": "FORTALEZA",
    "COD_IDENT_PROV": "Z",
    "FE_ALTA": "2000-04-15T00:00:00",
    "COD_ESTADO": "A",
    "FE_ULT_ACT": "2000-04-15T00:00:00"
  },
  {
    "COD_LOCALIDAD": 20348,
    "COD_POSTAL_VIEJO": 9401,
    "NOM_LOCALIDAD": "FUENTES DE COYLE",
    "COD_IDENT_PROV": "Z",
    "FE_ALTA": "2000-04-15T00:00:00",
    "COD_ESTADO": "A",
    "FE_ULT_ACT": "2000-04-15T00:00:00"
  },
  {
    "COD_LOCALIDAD": 20349,
    "COD_POSTAL_VIEJO": 9303,
    "NOM_LOCALIDAD": "GARMINUE",
    "COD_IDENT_PROV": "Z",
    "FE_ALTA": "2000-04-15T00:00:00",
    "COD_ESTADO": "A",
    "FE_ULT_ACT": "2000-04-15T00:00:00"
  },
  {
    "COD_LOCALIDAD": 20350,
    "COD_POSTAL_VIEJO": 9398,
    "NOM_LOCALIDAD": "GAYPON",
    "COD_IDENT_PROV": "Z",
    "FE_ALTA": "2004-02-15T01:39:32.302816",
    "COD_ESTADO": "A",
    "FE_ULT_ACT": "2004-02-15T01:39:32.302816"
  },
  {
    "COD_LOCALIDAD": 20350,
    "COD_POSTAL_VIEJO": 9407,
    "NOM_LOCALIDAD": "GAYPON",
    "COD_IDENT_PROV": "Z",
    "FE_ALTA": "2000-04-15T00:00:00",
    "COD_ESTADO": "A",
    "FE_ULT_ACT": "2000-04-15T00:00:00"
  },
  {
    "COD_LOCALIDAD": 20350,
    "COD_POSTAL_VIEJO": 9408,
    "NOM_LOCALIDAD": "GAYPON",
    "COD_IDENT_PROV": "Z",
    "FE_ALTA": "2004-02-15T01:39:32.302816",
    "COD_ESTADO": "A",
    "FE_ULT_ACT": "2004-02-15T01:39:32.302816"
  },
  {
    "COD_LOCALIDAD": 20351,
    "COD_POSTAL_VIEJO": 9398,
    "NOM_LOCALIDAD": "GLENCROSS",
    "COD_IDENT_PROV": "Z",
    "FE_ALTA": "2004-02-15T01:39:32.302816",
    "COD_ESTADO": "A",
    "FE_ULT_ACT": "2004-02-15T01:39:32.302816"
  },
  {
    "COD_LOCALIDAD": 20351,
    "COD_POSTAL_VIEJO": 9407,
    "NOM_LOCALIDAD": "GLENCROSS",
    "COD_IDENT_PROV": "Z",
    "FE_ALTA": "2000-04-15T00:00:00",
    "COD_ESTADO": "A",
    "FE_ULT_ACT": "2000-04-15T00:00:00"
  },
  {
    "COD_LOCALIDAD": 20351,
    "COD_POSTAL_VIEJO": 9408,
    "NOM_LOCALIDAD": "GLENCROSS",
    "COD_IDENT_PROV": "Z",
    "FE_ALTA": "2004-02-15T01:39:32.302816",
    "COD_ESTADO": "A",
    "FE_ULT_ACT": "2004-02-15T01:39:32.302816"
  },
  {
    "COD_LOCALIDAD": 20352,
    "COD_POSTAL_VIEJO": 9311,
    "NOM_LOCALIDAD": "GOBERNADOR GREGORES",
    "COD_IDENT_PROV": "Z",
    "FE_ALTA": "2000-04-15T00:00:00",
    "COD_ESTADO": "A",
    "FE_ULT_ACT": "2000-04-15T00:00:00"
  },
  {
    "COD_LOCALIDAD": 20353,
    "COD_POSTAL_VIEJO": 9401,
    "NOM_LOCALIDAD": "GOBERNADOR MAYER",
    "COD_IDENT_PROV": "Z",
    "FE_ALTA": "2000-04-15T00:00:00",
    "COD_ESTADO": "A",
    "FE_ULT_ACT": "2000-04-15T00:00:00"
  },
  {
    "COD_LOCALIDAD": 20354,
    "COD_POSTAL_VIEJO": 9050,
    "NOM_LOCALIDAD": "GOBERNADOR MOYANO",
    "COD_IDENT_PROV": "Z",
    "FE_ALTA": "2000-04-15T00:00:00",
    "COD_ESTADO": "A",
    "FE_ULT_ACT": "2000-04-15T00:00:00"
  },
  {
    "COD_LOCALIDAD": 20355,
    "COD_POSTAL_VIEJO": 9301,
    "NOM_LOCALIDAD": "GUARDAPARQUE FITZ ROY",
    "COD_IDENT_PROV": "Z",
    "FE_ALTA": "2000-04-15T00:00:00",
    "COD_ESTADO": "A",
    "FE_ULT_ACT": "2000-04-15T00:00:00"
  },
  {
    "COD_LOCALIDAD": 20356,
    "COD_POSTAL_VIEJO": 9315,
    "NOM_LOCALIDAD": "HOTEL LAS HORQUETAS",
    "COD_IDENT_PROV": "Z",
    "FE_ALTA": "2000-04-15T00:00:00",
    "COD_ESTADO": "A",
    "FE_ULT_ACT": "2000-04-15T00:00:00"
  },
  {
    "COD_LOCALIDAD": 20357,
    "COD_POSTAL_VIEJO": 9017,
    "NOM_LOCALIDAD": "INDIA MUERTA",
    "COD_IDENT_PROV": "Z",
    "FE_ALTA": "2000-04-15T00:00:00",
    "COD_ESTADO": "A",
    "FE_ULT_ACT": "2000-04-15T00:00:00"
  },
  {
    "COD_LOCALIDAD": 20358,
    "COD_POSTAL_VIEJO": 9400,
    "NOM_LOCALIDAD": "INGENIERO ATILIO CAPPA",
    "COD_IDENT_PROV": "Z",
    "FE_ALTA": "2000-04-15T00:00:00",
    "COD_ESTADO": "A",
    "FE_ULT_ACT": "2000-04-15T00:00:00"
  },
  {
    "COD_LOCALIDAD": 20358,
    "COD_POSTAL_VIEJO": 9402,
    "NOM_LOCALIDAD": "INGENIERO ATILIO CAPPA",
    "COD_IDENT_PROV": "Z",
    "FE_ALTA": "2004-02-15T01:39:32.302816",
    "COD_ESTADO": "A",
    "FE_ULT_ACT": "2004-02-15T01:39:32.302816"
  },
  {
    "COD_LOCALIDAD": 20358,
    "COD_POSTAL_VIEJO": 9403,
    "NOM_LOCALIDAD": "INGENIERO ATILIO CAPPA",
    "COD_IDENT_PROV": "Z",
    "FE_ALTA": "2004-02-15T01:39:32.302816",
    "COD_ESTADO": "A",
    "FE_ULT_ACT": "2004-02-15T01:39:32.302816"
  },
  {
    "COD_LOCALIDAD": 20359,
    "COD_POSTAL_VIEJO": 9040,
    "NOM_LOCALIDAD": "INGENIERO PALLAVICINI",
    "COD_IDENT_PROV": "Z",
    "FE_ALTA": "2000-04-15T00:00:00",
    "COD_ESTADO": "A",
    "FE_ULT_ACT": "2000-04-15T00:00:00"
  },
  {
    "COD_LOCALIDAD": 20360,
    "COD_POSTAL_VIEJO": 9053,
    "NOM_LOCALIDAD": "JARAMILLO",
    "COD_IDENT_PROV": "Z",
    "FE_ALTA": "2000-04-15T00:00:00",
    "COD_ESTADO": "A",
    "FE_ULT_ACT": "2000-04-15T00:00:00"
  },
  {
    "COD_LOCALIDAD": 20361,
    "COD_POSTAL_VIEJO": 9015,
    "NOM_LOCALIDAD": "JELAINA",
    "COD_IDENT_PROV": "Z",
    "FE_ALTA": "2000-04-15T00:00:00",
    "COD_ESTADO": "A",
    "FE_ULT_ACT": "2000-04-15T00:00:00"
  },
  {
    "COD_LOCALIDAD": 20362,
    "COD_POSTAL_VIEJO": 9398,
    "NOM_LOCALIDAD": "JULIA DUFOUR",
    "COD_IDENT_PROV": "Z",
    "FE_ALTA": "2004-02-15T01:39:32.302816",
    "COD_ESTADO": "A",
    "FE_ULT_ACT": "2004-02-15T01:39:32.302816"
  },
  {
    "COD_LOCALIDAD": 20362,
    "COD_POSTAL_VIEJO": 9407,
    "NOM_LOCALIDAD": "JULIA DUFOUR",
    "COD_IDENT_PROV": "Z",
    "FE_ALTA": "2000-04-15T00:00:00",
    "COD_ESTADO": "A",
    "FE_ULT_ACT": "2000-04-15T00:00:00"
  },
  {
    "COD_LOCALIDAD": 20362,
    "COD_POSTAL_VIEJO": 9408,
    "NOM_LOCALIDAD": "JULIA DUFOUR",
    "COD_IDENT_PROV": "Z",
    "FE_ALTA": "2004-02-15T01:39:32.302816",
    "COD_ESTADO": "A",
    "FE_ULT_ACT": "2004-02-15T01:39:32.302816"
  },
  {
    "COD_LOCALIDAD": 20363,
    "COD_POSTAL_VIEJO": 9050,
    "NOM_LOCALIDAD": "KILOMETRO 8",
    "COD_IDENT_PROV": "Z",
    "FE_ALTA": "2000-04-15T00:00:00",
    "COD_ESTADO": "A",
    "FE_ULT_ACT": "2000-04-15T00:00:00"
  },
  {
    "COD_LOCALIDAD": 20364,
    "COD_POSTAL_VIEJO": 9018,
    "NOM_LOCALIDAD": "KOLUEL KAIKE",
    "COD_IDENT_PROV": "Z",
    "FE_ALTA": "2004-02-15T01:39:32.302816",
    "COD_ESTADO": "A",
    "FE_ULT_ACT": "2004-02-15T01:39:32.302816"
  },
  {
    "COD_LOCALIDAD": 20364,
    "COD_POSTAL_VIEJO": 9019,
    "NOM_LOCALIDAD": "KOLUEL KAIKE",
    "COD_IDENT_PROV": "Z",
    "FE_ALTA": "2000-04-15T00:00:00",
    "COD_ESTADO": "A",
    "FE_ULT_ACT": "2000-04-15T00:00:00"
  },
  {
    "COD_LOCALIDAD": 20365,
    "COD_POSTAL_VIEJO": 9051,
    "NOM_LOCALIDAD": "LA AGUADA",
    "COD_IDENT_PROV": "Z",
    "FE_ALTA": "2000-04-15T00:00:00",
    "COD_ESTADO": "A",
    "FE_ULT_ACT": "2000-04-15T00:00:00"
  },
  {
    "COD_LOCALIDAD": 20366,
    "COD_POSTAL_VIEJO": 9015,
    "NOM_LOCALIDAD": "LA ANTONIA",
    "COD_IDENT_PROV": "Z",
    "FE_ALTA": "2000-04-15T00:00:00",
    "COD_ESTADO": "A",
    "FE_ULT_ACT": "2000-04-15T00:00:00"
  },
  {
    "COD_LOCALIDAD": 20367,
    "COD_POSTAL_VIEJO": 9017,
    "NOM_LOCALIDAD": "LA ARGENTINA",
    "COD_IDENT_PROV": "Z",
    "FE_ALTA": "2000-04-15T00:00:00",
    "COD_ESTADO": "A",
    "FE_ULT_ACT": "2000-04-15T00:00:00"
  },
  {
    "COD_LOCALIDAD": 20368,
    "COD_POSTAL_VIEJO": 9040,
    "NOM_LOCALIDAD": "LA ASTURIANA",
    "COD_IDENT_PROV": "Z",
    "FE_ALTA": "2000-04-15T00:00:00",
    "COD_ESTADO": "A",
    "FE_ULT_ACT": "2000-04-15T00:00:00"
  },
  {
    "COD_LOCALIDAD": 20369,
    "COD_POSTAL_VIEJO": 9303,
    "NOM_LOCALIDAD": "LA BARRETA",
    "COD_IDENT_PROV": "Z",
    "FE_ALTA": "2000-04-15T00:00:00",
    "COD_ESTADO": "A",
    "FE_ULT_ACT": "2000-04-15T00:00:00"
  },
  {
    "COD_LOCALIDAD": 20370,
    "COD_POSTAL_VIEJO": 9051,
    "NOM_LOCALIDAD": "LA CENTRAL",
    "COD_IDENT_PROV": "Z",
    "FE_ALTA": "2000-04-15T00:00:00",
    "COD_ESTADO": "A",
    "FE_ULT_ACT": "2000-04-15T00:00:00"
  },
  {
    "COD_LOCALIDAD": 20371,
    "COD_POSTAL_VIEJO": 9401,
    "NOM_LOCALIDAD": "LA ESPERANZA",
    "COD_IDENT_PROV": "Z",
    "FE_ALTA": "2000-04-15T00:00:00",
    "COD_ESTADO": "A",
    "FE_ULT_ACT": "2000-04-15T00:00:00"
  },
  {
    "COD_LOCALIDAD": 20372,
    "COD_POSTAL_VIEJO": 9051,
    "NOM_LOCALIDAD": "LA ESTELA",
    "COD_IDENT_PROV": "Z",
    "FE_ALTA": "2000-04-15T00:00:00",
    "COD_ESTADO": "A",
    "FE_ULT_ACT": "2000-04-15T00:00:00"
  },
  {
    "COD_LOCALIDAD": 20373,
    "COD_POSTAL_VIEJO": 9011,
    "NOM_LOCALIDAD": "LA ESTHER",
    "COD_IDENT_PROV": "Z",
    "FE_ALTA": "2000-04-15T00:00:00",
    "COD_ESTADO": "A",
    "FE_ULT_ACT": "2000-04-15T00:00:00"
  },
  {
    "COD_LOCALIDAD": 20374,
    "COD_POSTAL_VIEJO": 9051,
    "NOM_LOCALIDAD": "LA FECUNDIDAD",
    "COD_IDENT_PROV": "Z",
    "FE_ALTA": "2000-04-15T00:00:00",
    "COD_ESTADO": "A",
    "FE_ULT_ACT": "2000-04-15T00:00:00"
  },
  {
    "COD_LOCALIDAD": 20375,
    "COD_POSTAL_VIEJO": 9301,
    "NOM_LOCALIDAD": "LA FEDERICA",
    "COD_IDENT_PROV": "Z",
    "FE_ALTA": "2000-04-15T00:00:00",
    "COD_ESTADO": "A",
    "FE_ULT_ACT": "2000-04-15T00:00:00"
  },
  {
    "COD_LOCALIDAD": 20376,
    "COD_POSTAL_VIEJO": 9301,
    "NOM_LOCALIDAD": "LA FLORIDA",
    "COD_IDENT_PROV": "Z",
    "FE_ALTA": "2000-04-15T00:00:00",
    "COD_ESTADO": "A",
    "FE_ULT_ACT": "2000-04-15T00:00:00"
  },
  {
    "COD_LOCALIDAD": 20377,
    "COD_POSTAL_VIEJO": 9015,
    "NOM_LOCALIDAD": "LA GUARDIA",
    "COD_IDENT_PROV": "Z",
    "FE_ALTA": "2000-04-15T00:00:00",
    "COD_ESTADO": "A",
    "FE_ULT_ACT": "2000-04-15T00:00:00"
  },
  {
    "COD_LOCALIDAD": 20378,
    "COD_POSTAL_VIEJO": 9303,
    "NOM_LOCALIDAD": "LA JULIA",
    "COD_IDENT_PROV": "Z",
    "FE_ALTA": "2000-04-15T00:00:00",
    "COD_ESTADO": "A",
    "FE_ULT_ACT": "2000-04-15T00:00:00"
  },
  {
    "COD_LOCALIDAD": 20379,
    "COD_POSTAL_VIEJO": 9303,
    "NOM_LOCALIDAD": "LA LEONA",
    "COD_IDENT_PROV": "Z",
    "FE_ALTA": "2000-04-15T00:00:00",
    "COD_ESTADO": "A",
    "FE_ULT_ACT": "2000-04-15T00:00:00"
  },
  {
    "COD_LOCALIDAD": 20380,
    "COD_POSTAL_VIEJO": 9051,
    "NOM_LOCALIDAD": "LA MADRUGADA",
    "COD_IDENT_PROV": "Z",
    "FE_ALTA": "2000-04-15T00:00:00",
    "COD_ESTADO": "A",
    "FE_ULT_ACT": "2000-04-15T00:00:00"
  },
  {
    "COD_LOCALIDAD": 20381,
    "COD_POSTAL_VIEJO": 9311,
    "NOM_LOCALIDAD": "LA MANCHURIA",
    "COD_IDENT_PROV": "Z",
    "FE_ALTA": "2000-04-15T00:00:00",
    "COD_ESTADO": "A",
    "FE_ULT_ACT": "2000-04-15T00:00:00"
  },
  {
    "COD_LOCALIDAD": 20382,
    "COD_POSTAL_VIEJO": 9051,
    "NOM_LOCALIDAD": "LA MARGARITA",
    "COD_IDENT_PROV": "Z",
    "FE_ALTA": "2000-04-15T00:00:00",
    "COD_ESTADO": "A",
    "FE_ULT_ACT": "2000-04-15T00:00:00"
  },
  {
    "COD_LOCALIDAD": 20383,
    "COD_POSTAL_VIEJO": 9017,
    "NOM_LOCALIDAD": "LA MARIA",
    "COD_IDENT_PROV": "Z",
    "FE_ALTA": "2000-04-15T00:00:00",
    "COD_ESTADO": "A",
    "FE_ULT_ACT": "2000-04-15T00:00:00"
  },
  {
    "COD_LOCALIDAD": 20384,
    "COD_POSTAL_VIEJO": 9311,
    "NOM_LOCALIDAD": "LA PENINSULA",
    "COD_IDENT_PROV": "Z",
    "FE_ALTA": "2000-04-15T00:00:00",
    "COD_ESTADO": "A",
    "FE_ULT_ACT": "2000-04-15T00:00:00"
  },
  {
    "COD_LOCALIDAD": 20385,
    "COD_POSTAL_VIEJO": 9303,
    "NOM_LOCALIDAD": "LA PIGMEA",
    "COD_IDENT_PROV": "Z",
    "FE_ALTA": "2000-04-15T00:00:00",
    "COD_ESTADO": "A",
    "FE_ULT_ACT": "2000-04-15T00:00:00"
  },
  {
    "COD_LOCALIDAD": 20386,
    "COD_POSTAL_VIEJO": 9303,
    "NOM_LOCALIDAD": "LA PORTEÑA",
    "COD_IDENT_PROV": "Z",
    "FE_ALTA": "2000-04-15T00:00:00",
    "COD_ESTADO": "A",
    "FE_ULT_ACT": "2000-04-15T00:00:00"
  },
  {
    "COD_LOCALIDAD": 20387,
    "COD_POSTAL_VIEJO": 9051,
    "NOM_LOCALIDAD": "LA PROTEGIDA",
    "COD_IDENT_PROV": "Z",
    "FE_ALTA": "2000-04-15T00:00:00",
    "COD_ESTADO": "A",
    "FE_ULT_ACT": "2000-04-15T00:00:00"
  },
  {
    "COD_LOCALIDAD": 20388,
    "COD_POSTAL_VIEJO": 9015,
    "NOM_LOCALIDAD": "LA ROSA",
    "COD_IDENT_PROV": "Z",
    "FE_ALTA": "2000-04-15T00:00:00",
    "COD_ESTADO": "A",
    "FE_ULT_ACT": "2000-04-15T00:00:00"
  },
  {
    "COD_LOCALIDAD": 20389,
    "COD_POSTAL_VIEJO": 9051,
    "NOM_LOCALIDAD": "LA ROSADA",
    "COD_IDENT_PROV": "Z",
    "FE_ALTA": "2000-04-15T00:00:00",
    "COD_ESTADO": "A",
    "FE_ULT_ACT": "2000-04-15T00:00:00"
  },
  {
    "COD_LOCALIDAD": 20390,
    "COD_POSTAL_VIEJO": 9051,
    "NOM_LOCALIDAD": "LA VICTORIA",
    "COD_IDENT_PROV": "Z",
    "FE_ALTA": "2000-04-15T00:00:00",
    "COD_ESTADO": "A",
    "FE_ULT_ACT": "2000-04-15T00:00:00"
  },
  {
    "COD_LOCALIDAD": 20391,
    "COD_POSTAL_VIEJO": 9051,
    "NOM_LOCALIDAD": "LA VIOLETA",
    "COD_IDENT_PROV": "Z",
    "FE_ALTA": "2000-04-15T00:00:00",
    "COD_ESTADO": "A",
    "FE_ULT_ACT": "2000-04-15T00:00:00"
  },
  {
    "COD_LOCALIDAD": 20392,
    "COD_POSTAL_VIEJO": 9404,
    "NOM_LOCALIDAD": "LAGO ARGENTINO",
    "COD_IDENT_PROV": "Z",
    "FE_ALTA": "2004-02-15T01:39:32.302816",
    "COD_ESTADO": "A",
    "FE_ULT_ACT": "2004-02-15T01:39:32.302816"
  },
  {
    "COD_LOCALIDAD": 20392,
    "COD_POSTAL_VIEJO": 9405,
    "NOM_LOCALIDAD": "LAGO ARGENTINO",
    "COD_IDENT_PROV": "Z",
    "FE_ALTA": "2000-04-15T00:00:00",
    "COD_ESTADO": "A",
    "FE_ULT_ACT": "2000-04-15T00:00:00"
  },
  {
    "COD_LOCALIDAD": 20393,
    "COD_POSTAL_VIEJO": 9017,
    "NOM_LOCALIDAD": "LAGO BUENOS AIRES",
    "COD_IDENT_PROV": "Z",
    "FE_ALTA": "2000-04-15T00:00:00",
    "COD_ESTADO": "A",
    "FE_ULT_ACT": "2000-04-15T00:00:00"
  },
  {
    "COD_LOCALIDAD": 20393,
    "COD_POSTAL_VIEJO": 9040,
    "NOM_LOCALIDAD": "LAGO BUENOS AIRES",
    "COD_IDENT_PROV": "Z",
    "FE_ALTA": "2000-04-15T00:00:00",
    "COD_ESTADO": "A",
    "FE_ULT_ACT": "2000-04-15T00:00:00"
  },
  {
    "COD_LOCALIDAD": 20394,
    "COD_POSTAL_VIEJO": 9301,
    "NOM_LOCALIDAD": "LAGO CARDIEL",
    "COD_IDENT_PROV": "Z",
    "FE_ALTA": "2000-04-15T00:00:00",
    "COD_ESTADO": "A",
    "FE_ULT_ACT": "2000-04-15T00:00:00"
  },
  {
    "COD_LOCALIDAD": 20395,
    "COD_POSTAL_VIEJO": 9315,
    "NOM_LOCALIDAD": "LAGO POSADAS",
    "COD_IDENT_PROV": "Z",
    "FE_ALTA": "2000-04-15T00:00:00",
    "COD_ESTADO": "A",
    "FE_ULT_ACT": "2000-04-15T00:00:00"
  },
  {
    "COD_LOCALIDAD": 20396,
    "COD_POSTAL_VIEJO": 9310,
    "NOM_LOCALIDAD": "LAGO PUEYRREDON",
    "COD_IDENT_PROV": "Z",
    "FE_ALTA": "2000-04-15T00:00:00",
    "COD_ESTADO": "A",
    "FE_ULT_ACT": "2000-04-15T00:00:00"
  },
  {
    "COD_LOCALIDAD": 20397,
    "COD_POSTAL_VIEJO": 9404,
    "NOM_LOCALIDAD": "LAGO ROCA",
    "COD_IDENT_PROV": "Z",
    "FE_ALTA": "2004-02-15T01:39:32.302816",
    "COD_ESTADO": "A",
    "FE_ULT_ACT": "2004-02-15T01:39:32.302816"
  },
  {
    "COD_LOCALIDAD": 20397,
    "COD_POSTAL_VIEJO": 9405,
    "NOM_LOCALIDAD": "LAGO ROCA",
    "COD_IDENT_PROV": "Z",
    "FE_ALTA": "2000-04-15T00:00:00",
    "COD_ESTADO": "A",
    "FE_ULT_ACT": "2000-04-15T00:00:00"
  },
  {
    "COD_LOCALIDAD": 20398,
    "COD_POSTAL_VIEJO": 9301,
    "NOM_LOCALIDAD": "LAGO SAN MARTIN",
    "COD_IDENT_PROV": "Z",
    "FE_ALTA": "2000-04-15T00:00:00",
    "COD_ESTADO": "A",
    "FE_ULT_ACT": "2000-04-15T00:00:00"
  },
  {
    "COD_LOCALIDAD": 20399,
    "COD_POSTAL_VIEJO": 9311,
    "NOM_LOCALIDAD": "LAGO STROBEL",
    "COD_IDENT_PROV": "Z",
    "FE_ALTA": "2000-04-15T00:00:00",
    "COD_ESTADO": "A",
    "FE_ULT_ACT": "2000-04-15T00:00:00"
  },
  {
    "COD_LOCALIDAD": 20400,
    "COD_POSTAL_VIEJO": 9301,
    "NOM_LOCALIDAD": "LAGO TAR",
    "COD_IDENT_PROV": "Z",
    "FE_ALTA": "2000-04-15T00:00:00",
    "COD_ESTADO": "A",
    "FE_ULT_ACT": "2000-04-15T00:00:00"
  },
  {
    "COD_LOCALIDAD": 20401,
    "COD_POSTAL_VIEJO": 9400,
    "NOM_LOCALIDAD": "LAGUNA COLORADA",
    "COD_IDENT_PROV": "Z",
    "FE_ALTA": "2000-04-15T00:00:00",
    "COD_ESTADO": "A",
    "FE_ULT_ACT": "2000-04-15T00:00:00"
  },
  {
    "COD_LOCALIDAD": 20401,
    "COD_POSTAL_VIEJO": 9402,
    "NOM_LOCALIDAD": "LAGUNA COLORADA",
    "COD_IDENT_PROV": "Z",
    "FE_ALTA": "2004-02-15T01:39:32.302816",
    "COD_ESTADO": "A",
    "FE_ULT_ACT": "2004-02-15T01:39:32.302816"
  },
  {
    "COD_LOCALIDAD": 20401,
    "COD_POSTAL_VIEJO": 9403,
    "NOM_LOCALIDAD": "LAGUNA COLORADA",
    "COD_IDENT_PROV": "Z",
    "FE_ALTA": "2004-02-15T01:39:32.302816",
    "COD_ESTADO": "A",
    "FE_ULT_ACT": "2004-02-15T01:39:32.302816"
  },
  {
    "COD_LOCALIDAD": 20402,
    "COD_POSTAL_VIEJO": 9303,
    "NOM_LOCALIDAD": "LAGUNA GRANDE",
    "COD_IDENT_PROV": "Z",
    "FE_ALTA": "2000-04-15T00:00:00",
    "COD_ESTADO": "A",
    "FE_ULT_ACT": "2000-04-15T00:00:00"
  },
  {
    "COD_LOCALIDAD": 20403,
    "COD_POSTAL_VIEJO": 9017,
    "NOM_LOCALIDAD": "LAS HERAS",
    "COD_IDENT_PROV": "Z",
    "FE_ALTA": "2000-04-15T00:00:00",
    "COD_ESTADO": "A",
    "FE_ULT_ACT": "2000-04-15T00:00:00"
  },
  {
    "COD_LOCALIDAD": 20404,
    "COD_POSTAL_VIEJO": 9400,
    "NOM_LOCALIDAD": "LAS HORQUETAS",
    "COD_IDENT_PROV": "Z",
    "FE_ALTA": "2000-04-15T00:00:00",
    "COD_ESTADO": "A",
    "FE_ULT_ACT": "2000-04-15T00:00:00"
  },
  {
    "COD_LOCALIDAD": 20404,
    "COD_POSTAL_VIEJO": 9402,
    "NOM_LOCALIDAD": "LAS HORQUETAS",
    "COD_IDENT_PROV": "Z",
    "FE_ALTA": "2004-02-15T01:39:32.302816",
    "COD_ESTADO": "A",
    "FE_ULT_ACT": "2004-02-15T01:39:32.302816"
  },
  {
    "COD_LOCALIDAD": 20404,
    "COD_POSTAL_VIEJO": 9403,
    "NOM_LOCALIDAD": "LAS HORQUETAS",
    "COD_IDENT_PROV": "Z",
    "FE_ALTA": "2004-02-15T01:39:32.302816",
    "COD_ESTADO": "A",
    "FE_ULT_ACT": "2004-02-15T01:39:32.302816"
  },
  {
    "COD_LOCALIDAD": 20405,
    "COD_POSTAL_VIEJO": 9017,
    "NOM_LOCALIDAD": "LAS MASITAS",
    "COD_IDENT_PROV": "Z",
    "FE_ALTA": "2000-04-15T00:00:00",
    "COD_ESTADO": "A",
    "FE_ULT_ACT": "2000-04-15T00:00:00"
  },
  {
    "COD_LOCALIDAD": 20406,
    "COD_POSTAL_VIEJO": 9303,
    "NOM_LOCALIDAD": "LAS MERCEDES",
    "COD_IDENT_PROV": "Z",
    "FE_ALTA": "2000-04-15T00:00:00",
    "COD_ESTADO": "A",
    "FE_ULT_ACT": "2000-04-15T00:00:00"
  },
  {
    "COD_LOCALIDAD": 20407,
    "COD_POSTAL_VIEJO": 9017,
    "NOM_LOCALIDAD": "LAS PIRAMIDES",
    "COD_IDENT_PROV": "Z",
    "FE_ALTA": "2000-04-15T00:00:00",
    "COD_ESTADO": "A",
    "FE_ULT_ACT": "2000-04-15T00:00:00"
  },
  {
    "COD_LOCALIDAD": 20408,
    "COD_POSTAL_VIEJO": 9017,
    "NOM_LOCALIDAD": "LEANDRO NICEFORO ALEM",
    "COD_IDENT_PROV": "Z",
    "FE_ALTA": "2000-04-15T00:00:00",
    "COD_ESTADO": "A",
    "FE_ULT_ACT": "2000-04-15T00:00:00"
  },
  {
    "COD_LOCALIDAD": 20409,
    "COD_POSTAL_VIEJO": 9041,
    "NOM_LOCALIDAD": "LOS ANTIGUOS",
    "COD_IDENT_PROV": "Z",
    "FE_ALTA": "2000-04-15T00:00:00",
    "COD_ESTADO": "A",
    "FE_ULT_ACT": "2000-04-15T00:00:00"
  },
  {
    "COD_LOCALIDAD": 20410,
    "COD_POSTAL_VIEJO": 9313,
    "NOM_LOCALIDAD": "LOS MANANTIALES",
    "COD_IDENT_PROV": "Z",
    "FE_ALTA": "2000-04-15T00:00:00",
    "COD_ESTADO": "A",
    "FE_ULT_ACT": "2000-04-15T00:00:00"
  },
  {
    "COD_LOCALIDAD": 20411,
    "COD_POSTAL_VIEJO": 9017,
    "NOM_LOCALIDAD": "MATA MAGALLANES",
    "COD_IDENT_PROV": "Z",
    "FE_ALTA": "2000-04-15T00:00:00",
    "COD_ESTADO": "A",
    "FE_ULT_ACT": "2000-04-15T00:00:00"
  },
  {
    "COD_LOCALIDAD": 20412,
    "COD_POSTAL_VIEJO": 9051,
    "NOM_LOCALIDAD": "MAZAREDO",
    "COD_IDENT_PROV": "Z",
    "FE_ALTA": "2000-04-15T00:00:00",
    "COD_ESTADO": "A",
    "FE_ULT_ACT": "2000-04-15T00:00:00"
  },
  {
    "COD_LOCALIDAD": 20413,
    "COD_POSTAL_VIEJO": 9017,
    "NOM_LOCALIDAD": "MESETA GUENGUE",
    "COD_IDENT_PROV": "Z",
    "FE_ALTA": "2000-04-15T00:00:00",
    "COD_ESTADO": "A",
    "FE_ULT_ACT": "2000-04-15T00:00:00"
  },
  {
    "COD_LOCALIDAD": 20414,
    "COD_POSTAL_VIEJO": 9398,
    "NOM_LOCALIDAD": "MINA 3",
    "COD_IDENT_PROV": "Z",
    "FE_ALTA": "2004-02-15T01:39:32.302816",
    "COD_ESTADO": "A",
    "FE_ULT_ACT": "2004-02-15T01:39:32.302816"
  },
  {
    "COD_LOCALIDAD": 20414,
    "COD_POSTAL_VIEJO": 9407,
    "NOM_LOCALIDAD": "MINA 3",
    "COD_IDENT_PROV": "Z",
    "FE_ALTA": "2000-04-15T00:00:00",
    "COD_ESTADO": "A",
    "FE_ULT_ACT": "2000-04-15T00:00:00"
  },
  {
    "COD_LOCALIDAD": 20414,
    "COD_POSTAL_VIEJO": 9408,
    "NOM_LOCALIDAD": "MINA 3",
    "COD_IDENT_PROV": "Z",
    "FE_ALTA": "2004-02-15T01:39:32.302816",
    "COD_ESTADO": "A",
    "FE_ULT_ACT": "2004-02-15T01:39:32.302816"
  },
  {
    "COD_LOCALIDAD": 20415,
    "COD_POSTAL_VIEJO": 9015,
    "NOM_LOCALIDAD": "MINERALES",
    "COD_IDENT_PROV": "Z",
    "FE_ALTA": "2000-04-15T00:00:00",
    "COD_ESTADO": "A",
    "FE_ULT_ACT": "2000-04-15T00:00:00"
  },
  {
    "COD_LOCALIDAD": 20416,
    "COD_POSTAL_VIEJO": 9400,
    "NOM_LOCALIDAD": "MONTE AYMOND",
    "COD_IDENT_PROV": "Z",
    "FE_ALTA": "2000-04-15T00:00:00",
    "COD_ESTADO": "A",
    "FE_ULT_ACT": "2000-04-15T00:00:00"
  },
  {
    "COD_LOCALIDAD": 20416,
    "COD_POSTAL_VIEJO": 9402,
    "NOM_LOCALIDAD": "MONTE AYMOND",
    "COD_IDENT_PROV": "Z",
    "FE_ALTA": "2004-02-15T01:39:32.302816",
    "COD_ESTADO": "A",
    "FE_ULT_ACT": "2004-02-15T01:39:32.302816"
  },
  {
    "COD_LOCALIDAD": 20416,
    "COD_POSTAL_VIEJO": 9403,
    "NOM_LOCALIDAD": "MONTE AYMOND",
    "COD_IDENT_PROV": "Z",
    "FE_ALTA": "2004-02-15T01:39:32.302816",
    "COD_ESTADO": "A",
    "FE_ULT_ACT": "2004-02-15T01:39:32.302816"
  },
  {
    "COD_LOCALIDAD": 20417,
    "COD_POSTAL_VIEJO": 9040,
    "NOM_LOCALIDAD": "MONTE CEBALLOS",
    "COD_IDENT_PROV": "Z",
    "FE_ALTA": "2000-04-15T00:00:00",
    "COD_ESTADO": "A",
    "FE_ULT_ACT": "2000-04-15T00:00:00"
  },
  {
    "COD_LOCALIDAD": 20418,
    "COD_POSTAL_VIEJO": 9018,
    "NOM_LOCALIDAD": "MONTE VERDE",
    "COD_IDENT_PROV": "Z",
    "FE_ALTA": "2004-02-15T01:39:32.302816",
    "COD_ESTADO": "A",
    "FE_ULT_ACT": "2004-02-15T01:39:32.302816"
  },
  {
    "COD_LOCALIDAD": 20418,
    "COD_POSTAL_VIEJO": 9019,
    "NOM_LOCALIDAD": "MONTE VERDE",
    "COD_IDENT_PROV": "Z",
    "FE_ALTA": "2000-04-15T00:00:00",
    "COD_ESTADO": "A",
    "FE_ULT_ACT": "2000-04-15T00:00:00"
  },
  {
    "COD_LOCALIDAD": 20419,
    "COD_POSTAL_VIEJO": 9398,
    "NOM_LOCALIDAD": "MORRO CHICO",
    "COD_IDENT_PROV": "Z",
    "FE_ALTA": "2004-02-15T01:39:32.302816",
    "COD_ESTADO": "A",
    "FE_ULT_ACT": "2004-02-15T01:39:32.302816"
  },
  {
    "COD_LOCALIDAD": 20419,
    "COD_POSTAL_VIEJO": 9407,
    "NOM_LOCALIDAD": "MORRO CHICO",
    "COD_IDENT_PROV": "Z",
    "FE_ALTA": "2000-04-15T00:00:00",
    "COD_ESTADO": "A",
    "FE_ULT_ACT": "2000-04-15T00:00:00"
  },
  {
    "COD_LOCALIDAD": 20419,
    "COD_POSTAL_VIEJO": 9408,
    "NOM_LOCALIDAD": "MORRO CHICO",
    "COD_IDENT_PROV": "Z",
    "FE_ALTA": "2004-02-15T01:39:32.302816",
    "COD_ESTADO": "A",
    "FE_ULT_ACT": "2004-02-15T01:39:32.302816"
  },
  {
    "COD_LOCALIDAD": 20420,
    "COD_POSTAL_VIEJO": 9040,
    "NOM_LOCALIDAD": "NACIMIENTOS DEL PLUMA",
    "COD_IDENT_PROV": "Z",
    "FE_ALTA": "2000-04-15T00:00:00",
    "COD_ESTADO": "A",
    "FE_ULT_ACT": "2000-04-15T00:00:00"
  },
  {
    "COD_LOCALIDAD": 20421,
    "COD_POSTAL_VIEJO": 9400,
    "NOM_LOCALIDAD": "PALERMO AIKE",
    "COD_IDENT_PROV": "Z",
    "FE_ALTA": "2000-04-15T00:00:00",
    "COD_ESTADO": "A",
    "FE_ULT_ACT": "2000-04-15T00:00:00"
  },
  {
    "COD_LOCALIDAD": 20421,
    "COD_POSTAL_VIEJO": 9402,
    "NOM_LOCALIDAD": "PALERMO AIKE",
    "COD_IDENT_PROV": "Z",
    "FE_ALTA": "2004-02-15T01:39:32.302816",
    "COD_ESTADO": "A",
    "FE_ULT_ACT": "2004-02-15T01:39:32.302816"
  },
  {
    "COD_LOCALIDAD": 20421,
    "COD_POSTAL_VIEJO": 9403,
    "NOM_LOCALIDAD": "PALERMO AIKE",
    "COD_IDENT_PROV": "Z",
    "FE_ALTA": "2004-02-15T01:39:32.302816",
    "COD_ESTADO": "A",
    "FE_ULT_ACT": "2004-02-15T01:39:32.302816"
  },
  {
    "COD_LOCALIDAD": 20422,
    "COD_POSTAL_VIEJO": 9400,
    "NOM_LOCALIDAD": "PALI AIKE",
    "COD_IDENT_PROV": "Z",
    "FE_ALTA": "2000-04-15T00:00:00",
    "COD_ESTADO": "A",
    "FE_ULT_ACT": "2000-04-15T00:00:00"
  },
  {
    "COD_LOCALIDAD": 20422,
    "COD_POSTAL_VIEJO": 9402,
    "NOM_LOCALIDAD": "PALI AIKE",
    "COD_IDENT_PROV": "Z",
    "FE_ALTA": "2004-02-15T01:39:32.302816",
    "COD_ESTADO": "A",
    "FE_ULT_ACT": "2004-02-15T01:39:32.302816"
  },
  {
    "COD_LOCALIDAD": 20422,
    "COD_POSTAL_VIEJO": 9403,
    "NOM_LOCALIDAD": "PALI AIKE",
    "COD_IDENT_PROV": "Z",
    "FE_ALTA": "2004-02-15T01:39:32.302816",
    "COD_ESTADO": "A",
    "FE_ULT_ACT": "2004-02-15T01:39:32.302816"
  },
  {
    "COD_LOCALIDAD": 20423,
    "COD_POSTAL_VIEJO": 9017,
    "NOM_LOCALIDAD": "PAMPA VERDUM",
    "COD_IDENT_PROV": "Z",
    "FE_ALTA": "2000-04-15T00:00:00",
    "COD_ESTADO": "A",
    "FE_ULT_ACT": "2000-04-15T00:00:00"
  },
  {
    "COD_LOCALIDAD": 20424,
    "COD_POSTAL_VIEJO": 9404,
    "NOM_LOCALIDAD": "PASO CHARLES FHUR",
    "COD_IDENT_PROV": "Z",
    "FE_ALTA": "2004-02-15T01:39:32.302816",
    "COD_ESTADO": "A",
    "FE_ULT_ACT": "2004-02-15T01:39:32.302816"
  },
  {
    "COD_LOCALIDAD": 20424,
    "COD_POSTAL_VIEJO": 9405,
    "NOM_LOCALIDAD": "PASO CHARLES FHUR",
    "COD_IDENT_PROV": "Z",
    "FE_ALTA": "2000-04-15T00:00:00",
    "COD_ESTADO": "A",
    "FE_ULT_ACT": "2000-04-15T00:00:00"
  },
  {
    "COD_LOCALIDAD": 20425,
    "COD_POSTAL_VIEJO": 9303,
    "NOM_LOCALIDAD": "PASO DE LOS INDIOS",
    "COD_IDENT_PROV": "Z",
    "FE_ALTA": "2000-04-15T00:00:00",
    "COD_ESTADO": "A",
    "FE_ULT_ACT": "2000-04-15T00:00:00"
  },
  {
    "COD_LOCALIDAD": 20426,
    "COD_POSTAL_VIEJO": 9311,
    "NOM_LOCALIDAD": "PASO DEL AGUILA",
    "COD_IDENT_PROV": "Z",
    "FE_ALTA": "2000-04-15T00:00:00",
    "COD_ESTADO": "A",
    "FE_ULT_ACT": "2000-04-15T00:00:00"
  },
  {
    "COD_LOCALIDAD": 20427,
    "COD_POSTAL_VIEJO": 9400,
    "NOM_LOCALIDAD": "PASO DEL MEDIO",
    "COD_IDENT_PROV": "Z",
    "FE_ALTA": "2000-04-15T00:00:00",
    "COD_ESTADO": "A",
    "FE_ULT_ACT": "2000-04-15T00:00:00"
  },
  {
    "COD_LOCALIDAD": 20427,
    "COD_POSTAL_VIEJO": 9402,
    "NOM_LOCALIDAD": "PASO DEL MEDIO",
    "COD_IDENT_PROV": "Z",
    "FE_ALTA": "2004-02-15T01:39:32.302816",
    "COD_ESTADO": "A",
    "FE_ULT_ACT": "2004-02-15T01:39:32.302816"
  },
  {
    "COD_LOCALIDAD": 20427,
    "COD_POSTAL_VIEJO": 9403,
    "NOM_LOCALIDAD": "PASO DEL MEDIO",
    "COD_IDENT_PROV": "Z",
    "FE_ALTA": "2004-02-15T01:39:32.302816",
    "COD_ESTADO": "A",
    "FE_ULT_ACT": "2004-02-15T01:39:32.302816"
  },
  {
    "COD_LOCALIDAD": 20428,
    "COD_POSTAL_VIEJO": 9303,
    "NOM_LOCALIDAD": "PASO DEL RIO SANTA CRUZ",
    "COD_IDENT_PROV": "Z",
    "FE_ALTA": "2000-04-15T00:00:00",
    "COD_ESTADO": "A",
    "FE_ULT_ACT": "2000-04-15T00:00:00"
  },
  {
    "COD_LOCALIDAD": 20429,
    "COD_POSTAL_VIEJO": 9050,
    "NOM_LOCALIDAD": "PASO GREGORES",
    "COD_IDENT_PROV": "Z",
    "FE_ALTA": "2000-04-15T00:00:00",
    "COD_ESTADO": "A",
    "FE_ULT_ACT": "2000-04-15T00:00:00"
  },
  {
    "COD_LOCALIDAD": 20430,
    "COD_POSTAL_VIEJO": 9303,
    "NOM_LOCALIDAD": "PASO IBAÑEZ",
    "COD_IDENT_PROV": "Z",
    "FE_ALTA": "2000-04-15T00:00:00",
    "COD_ESTADO": "A",
    "FE_ULT_ACT": "2000-04-15T00:00:00"
  },
  {
    "COD_LOCALIDAD": 20431,
    "COD_POSTAL_VIEJO": 9301,
    "NOM_LOCALIDAD": "PASO RIO LA LEONA",
    "COD_IDENT_PROV": "Z",
    "FE_ALTA": "2000-04-15T00:00:00",
    "COD_ESTADO": "A",
    "FE_ULT_ACT": "2000-04-15T00:00:00"
  },
  {
    "COD_LOCALIDAD": 20432,
    "COD_POSTAL_VIEJO": 9315,
    "NOM_LOCALIDAD": "PASO ROBALLO",
    "COD_IDENT_PROV": "Z",
    "FE_ALTA": "2000-04-15T00:00:00",
    "COD_ESTADO": "A",
    "FE_ULT_ACT": "2000-04-15T00:00:00"
  },
  {
    "COD_LOCALIDAD": 20433,
    "COD_POSTAL_VIEJO": 9017,
    "NOM_LOCALIDAD": "PELLEGRINI",
    "COD_IDENT_PROV": "Z",
    "FE_ALTA": "2000-04-15T00:00:00",
    "COD_ESTADO": "A",
    "FE_ULT_ACT": "2000-04-15T00:00:00"
  },
  {
    "COD_LOCALIDAD": 20434,
    "COD_POSTAL_VIEJO": 9301,
    "NOM_LOCALIDAD": "PENINSULA MAIPU",
    "COD_IDENT_PROV": "Z",
    "FE_ALTA": "2000-04-15T00:00:00",
    "COD_ESTADO": "A",
    "FE_ULT_ACT": "2000-04-15T00:00:00"
  },
  {
    "COD_LOCALIDAD": 20435,
    "COD_POSTAL_VIEJO": 9040,
    "NOM_LOCALIDAD": "PERITO MORENO",
    "COD_IDENT_PROV": "Z",
    "FE_ALTA": "2000-04-15T00:00:00",
    "COD_ESTADO": "A",
    "FE_ULT_ACT": "2000-04-15T00:00:00"
  },
  {
    "COD_LOCALIDAD": 20436,
    "COD_POSTAL_VIEJO": 9015,
    "NOM_LOCALIDAD": "PICO TRUNCADO",
    "COD_IDENT_PROV": "Z",
    "FE_ALTA": "2000-04-15T00:00:00",
    "COD_ESTADO": "A",
    "FE_ULT_ACT": "2000-04-15T00:00:00"
  },
  {
    "COD_LOCALIDAD": 20437,
    "COD_POSTAL_VIEJO": 9017,
    "NOM_LOCALIDAD": "PIEDRA CLAVADA",
    "COD_IDENT_PROV": "Z",
    "FE_ALTA": "2000-04-15T00:00:00",
    "COD_ESTADO": "A",
    "FE_ULT_ACT": "2000-04-15T00:00:00"
  },
  {
    "COD_LOCALIDAD": 20437,
    "COD_POSTAL_VIEJO": 9301,
    "NOM_LOCALIDAD": "PIEDRA CLAVADA",
    "COD_IDENT_PROV": "Z",
    "FE_ALTA": "2000-04-15T00:00:00",
    "COD_ESTADO": "A",
    "FE_ULT_ACT": "2000-04-15T00:00:00"
  },
  {
    "COD_LOCALIDAD": 20438,
    "COD_POSTAL_VIEJO": 9398,
    "NOM_LOCALIDAD": "PUEBLO NUEVO",
    "COD_IDENT_PROV": "Z",
    "FE_ALTA": "2004-02-15T01:39:32.302816",
    "COD_ESTADO": "A",
    "FE_ULT_ACT": "2004-02-15T01:39:32.302816"
  },
  {
    "COD_LOCALIDAD": 20438,
    "COD_POSTAL_VIEJO": 9407,
    "NOM_LOCALIDAD": "PUEBLO NUEVO",
    "COD_IDENT_PROV": "Z",
    "FE_ALTA": "2000-04-15T00:00:00",
    "COD_ESTADO": "A",
    "FE_ULT_ACT": "2000-04-15T00:00:00"
  },
  {
    "COD_LOCALIDAD": 20438,
    "COD_POSTAL_VIEJO": 9408,
    "NOM_LOCALIDAD": "PUEBLO NUEVO",
    "COD_IDENT_PROV": "Z",
    "FE_ALTA": "2004-02-15T01:39:32.302816",
    "COD_ESTADO": "A",
    "FE_ULT_ACT": "2004-02-15T01:39:32.302816"
  },
  {
    "COD_LOCALIDAD": 20439,
    "COD_POSTAL_VIEJO": 9398,
    "NOM_LOCALIDAD": "PUENTE BLANCO",
    "COD_IDENT_PROV": "Z",
    "FE_ALTA": "2004-02-15T01:39:32.302816",
    "COD_ESTADO": "A",
    "FE_ULT_ACT": "2004-02-15T01:39:32.302816"
  },
  {
    "COD_LOCALIDAD": 20439,
    "COD_POSTAL_VIEJO": 9407,
    "NOM_LOCALIDAD": "PUENTE BLANCO",
    "COD_IDENT_PROV": "Z",
    "FE_ALTA": "2000-04-15T00:00:00",
    "COD_ESTADO": "A",
    "FE_ULT_ACT": "2000-04-15T00:00:00"
  },
  {
    "COD_LOCALIDAD": 20439,
    "COD_POSTAL_VIEJO": 9408,
    "NOM_LOCALIDAD": "PUENTE BLANCO",
    "COD_IDENT_PROV": "Z",
    "FE_ALTA": "2004-02-15T01:39:32.302816",
    "COD_ESTADO": "A",
    "FE_ULT_ACT": "2004-02-15T01:39:32.302816"
  },
  {
    "COD_LOCALIDAD": 20440,
    "COD_POSTAL_VIEJO": 9050,
    "NOM_LOCALIDAD": "PUERTO DESEADO",
    "COD_IDENT_PROV": "Z",
    "FE_ALTA": "2000-04-15T00:00:00",
    "COD_ESTADO": "A",
    "FE_ULT_ACT": "2000-04-15T00:00:00"
  },
  {
    "COD_LOCALIDAD": 20441,
    "COD_POSTAL_VIEJO": 9310,
    "NOM_LOCALIDAD": "PUERTO SAN JULIAN",
    "COD_IDENT_PROV": "Z",
    "FE_ALTA": "2000-04-15T00:00:00",
    "COD_ESTADO": "A",
    "FE_ULT_ACT": "2000-04-15T00:00:00"
  },
  {
    "COD_LOCALIDAD": 20442,
    "COD_POSTAL_VIEJO": 9300,
    "NOM_LOCALIDAD": "PUERTO SANTA CRUZ",
    "COD_IDENT_PROV": "Z",
    "FE_ALTA": "2000-04-15T00:00:00",
    "COD_ESTADO": "A",
    "FE_ULT_ACT": "2000-04-15T00:00:00"
  },
  {
    "COD_LOCALIDAD": 20443,
    "COD_POSTAL_VIEJO": 9404,
    "NOM_LOCALIDAD": "PUNTA BANDERA",
    "COD_IDENT_PROV": "Z",
    "FE_ALTA": "2004-02-15T01:39:32.302816",
    "COD_ESTADO": "A",
    "FE_ULT_ACT": "2004-02-15T01:39:32.302816"
  },
  {
    "COD_LOCALIDAD": 20443,
    "COD_POSTAL_VIEJO": 9405,
    "NOM_LOCALIDAD": "PUNTA BANDERA",
    "COD_IDENT_PROV": "Z",
    "FE_ALTA": "2000-04-15T00:00:00",
    "COD_ESTADO": "A",
    "FE_ULT_ACT": "2000-04-15T00:00:00"
  },
  {
    "COD_LOCALIDAD": 20444,
    "COD_POSTAL_VIEJO": 9301,
    "NOM_LOCALIDAD": "PUNTA DEL LAGO VIEDMA",
    "COD_IDENT_PROV": "Z",
    "FE_ALTA": "2000-04-15T00:00:00",
    "COD_ESTADO": "A",
    "FE_ULT_ACT": "2000-04-15T00:00:00"
  },
  {
    "COD_LOCALIDAD": 20445,
    "COD_POSTAL_VIEJO": 9400,
    "NOM_LOCALIDAD": "PUNTA DEL MONTE",
    "COD_IDENT_PROV": "Z",
    "FE_ALTA": "2000-04-15T00:00:00",
    "COD_ESTADO": "A",
    "FE_ULT_ACT": "2000-04-15T00:00:00"
  },
  {
    "COD_LOCALIDAD": 20445,
    "COD_POSTAL_VIEJO": 9402,
    "NOM_LOCALIDAD": "PUNTA DEL MONTE",
    "COD_IDENT_PROV": "Z",
    "FE_ALTA": "2004-02-15T01:39:32.302816",
    "COD_ESTADO": "A",
    "FE_ULT_ACT": "2004-02-15T01:39:32.302816"
  },
  {
    "COD_LOCALIDAD": 20445,
    "COD_POSTAL_VIEJO": 9403,
    "NOM_LOCALIDAD": "PUNTA DEL MONTE",
    "COD_IDENT_PROV": "Z",
    "FE_ALTA": "2004-02-15T01:39:32.302816",
    "COD_ESTADO": "A",
    "FE_ULT_ACT": "2004-02-15T01:39:32.302816"
  },
  {
    "COD_LOCALIDAD": 20446,
    "COD_POSTAL_VIEJO": 9400,
    "NOM_LOCALIDAD": "PUNTA LOYOLA",
    "COD_IDENT_PROV": "Z",
    "FE_ALTA": "2000-04-15T00:00:00",
    "COD_ESTADO": "A",
    "FE_ULT_ACT": "2000-04-15T00:00:00"
  },
  {
    "COD_LOCALIDAD": 20446,
    "COD_POSTAL_VIEJO": 9402,
    "NOM_LOCALIDAD": "PUNTA LOYOLA",
    "COD_IDENT_PROV": "Z",
    "FE_ALTA": "2004-02-15T01:39:32.302816",
    "COD_ESTADO": "A",
    "FE_ULT_ACT": "2004-02-15T01:39:32.302816"
  },
  {
    "COD_LOCALIDAD": 20446,
    "COD_POSTAL_VIEJO": 9403,
    "NOM_LOCALIDAD": "PUNTA LOYOLA",
    "COD_IDENT_PROV": "Z",
    "FE_ALTA": "2004-02-15T01:39:32.302816",
    "COD_ESTADO": "A",
    "FE_ULT_ACT": "2004-02-15T01:39:32.302816"
  },
  {
    "COD_LOCALIDAD": 20447,
    "COD_POSTAL_VIEJO": 9313,
    "NOM_LOCALIDAD": "PUNTA MERCEDES",
    "COD_IDENT_PROV": "Z",
    "FE_ALTA": "2000-04-15T00:00:00",
    "COD_ESTADO": "A",
    "FE_ULT_ACT": "2000-04-15T00:00:00"
  },
  {
    "COD_LOCALIDAD": 20448,
    "COD_POSTAL_VIEJO": 9404,
    "NOM_LOCALIDAD": "QUIEN SABE",
    "COD_IDENT_PROV": "Z",
    "FE_ALTA": "2004-02-15T01:39:32.302816",
    "COD_ESTADO": "A",
    "FE_ULT_ACT": "2004-02-15T01:39:32.302816"
  },
  {
    "COD_LOCALIDAD": 20448,
    "COD_POSTAL_VIEJO": 9405,
    "NOM_LOCALIDAD": "QUIEN SABE",
    "COD_IDENT_PROV": "Z",
    "FE_ALTA": "2000-04-15T00:00:00",
    "COD_ESTADO": "A",
    "FE_ULT_ACT": "2000-04-15T00:00:00"
  },
  {
    "COD_LOCALIDAD": 20449,
    "COD_POSTAL_VIEJO": 9398,
    "NOM_LOCALIDAD": "RINCON DE LOS MORROS",
    "COD_IDENT_PROV": "Z",
    "FE_ALTA": "2004-02-15T01:39:32.302816",
    "COD_ESTADO": "A",
    "FE_ULT_ACT": "2004-02-15T01:39:32.302816"
  },
  {
    "COD_LOCALIDAD": 20449,
    "COD_POSTAL_VIEJO": 9407,
    "NOM_LOCALIDAD": "RINCON DE LOS MORROS",
    "COD_IDENT_PROV": "Z",
    "FE_ALTA": "2000-04-15T00:00:00",
    "COD_ESTADO": "A",
    "FE_ULT_ACT": "2000-04-15T00:00:00"
  },
  {
    "COD_LOCALIDAD": 20449,
    "COD_POSTAL_VIEJO": 9408,
    "NOM_LOCALIDAD": "RINCON DE LOS MORROS",
    "COD_IDENT_PROV": "Z",
    "FE_ALTA": "2004-02-15T01:39:32.302816",
    "COD_ESTADO": "A",
    "FE_ULT_ACT": "2004-02-15T01:39:32.302816"
  },
  {
    "COD_LOCALIDAD": 20450,
    "COD_POSTAL_VIEJO": 9404,
    "NOM_LOCALIDAD": "RIO BOTE",
    "COD_IDENT_PROV": "Z",
    "FE_ALTA": "2004-02-15T01:39:32.302816",
    "COD_ESTADO": "A",
    "FE_ULT_ACT": "2004-02-15T01:39:32.302816"
  },
  {
    "COD_LOCALIDAD": 20450,
    "COD_POSTAL_VIEJO": 9405,
    "NOM_LOCALIDAD": "RIO BOTE",
    "COD_IDENT_PROV": "Z",
    "FE_ALTA": "2000-04-15T00:00:00",
    "COD_ESTADO": "A",
    "FE_ULT_ACT": "2000-04-15T00:00:00"
  },
  {
    "COD_LOCALIDAD": 20451,
    "COD_POSTAL_VIEJO": 9404,
    "NOM_LOCALIDAD": "RIO CALAFATE",
    "COD_IDENT_PROV": "Z",
    "FE_ALTA": "2004-02-15T01:39:32.302816",
    "COD_ESTADO": "A",
    "FE_ULT_ACT": "2004-02-15T01:39:32.302816"
  },
  {
    "COD_LOCALIDAD": 20451,
    "COD_POSTAL_VIEJO": 9405,
    "NOM_LOCALIDAD": "RIO CALAFATE",
    "COD_IDENT_PROV": "Z",
    "FE_ALTA": "2000-04-15T00:00:00",
    "COD_ESTADO": "A",
    "FE_ULT_ACT": "2000-04-15T00:00:00"
  },
  {
    "COD_LOCALIDAD": 20452,
    "COD_POSTAL_VIEJO": 9303,
    "NOM_LOCALIDAD": "RIO CHICO",
    "COD_IDENT_PROV": "Z",
    "FE_ALTA": "2000-04-15T00:00:00",
    "COD_ESTADO": "A",
    "FE_ULT_ACT": "2000-04-15T00:00:00"
  },
  {
    "COD_LOCALIDAD": 20453,
    "COD_POSTAL_VIEJO": 9040,
    "NOM_LOCALIDAD": "RIO FENIX",
    "COD_IDENT_PROV": "Z",
    "FE_ALTA": "2000-04-15T00:00:00",
    "COD_ESTADO": "A",
    "FE_ULT_ACT": "2000-04-15T00:00:00"
  },
  {
    "COD_LOCALIDAD": 20454,
    "COD_POSTAL_VIEJO": 9400,
    "NOM_LOCALIDAD": "RIO GALLEGOS",
    "COD_IDENT_PROV": "Z",
    "FE_ALTA": "2000-04-15T00:00:00",
    "COD_ESTADO": "A",
    "FE_ULT_ACT": "2000-04-15T00:00:00"
  },
  {
    "COD_LOCALIDAD": 20454,
    "COD_POSTAL_VIEJO": 9402,
    "NOM_LOCALIDAD": "RIO GALLEGOS",
    "COD_IDENT_PROV": "Z",
    "FE_ALTA": "2004-02-15T01:39:32.302816",
    "COD_ESTADO": "A",
    "FE_ULT_ACT": "2004-02-15T01:39:32.302816"
  },
  {
    "COD_LOCALIDAD": 20454,
    "COD_POSTAL_VIEJO": 9403,
    "NOM_LOCALIDAD": "RIO GALLEGOS",
    "COD_IDENT_PROV": "Z",
    "FE_ALTA": "2004-02-15T01:39:32.302816",
    "COD_ESTADO": "A",
    "FE_ULT_ACT": "2004-02-15T01:39:32.302816"
  },
  {
    "COD_LOCALIDAD": 20455,
    "COD_POSTAL_VIEJO": 9404,
    "NOM_LOCALIDAD": "RIO MITRE",
    "COD_IDENT_PROV": "Z",
    "FE_ALTA": "2004-02-15T01:39:32.302816",
    "COD_ESTADO": "A",
    "FE_ULT_ACT": "2004-02-15T01:39:32.302816"
  },
  {
    "COD_LOCALIDAD": 20455,
    "COD_POSTAL_VIEJO": 9405,
    "NOM_LOCALIDAD": "RIO MITRE",
    "COD_IDENT_PROV": "Z",
    "FE_ALTA": "2000-04-15T00:00:00",
    "COD_ESTADO": "A",
    "FE_ULT_ACT": "2000-04-15T00:00:00"
  },
  {
    "COD_LOCALIDAD": 20456,
    "COD_POSTAL_VIEJO": 9398,
    "NOM_LOCALIDAD": "RIO TURBIO",
    "COD_IDENT_PROV": "Z",
    "FE_ALTA": "2004-02-15T01:39:32.302816",
    "COD_ESTADO": "A",
    "FE_ULT_ACT": "2004-02-15T01:39:32.302816"
  },
  {
    "COD_LOCALIDAD": 20456,
    "COD_POSTAL_VIEJO": 9407,
    "NOM_LOCALIDAD": "RIO TURBIO",
    "COD_IDENT_PROV": "Z",
    "FE_ALTA": "2000-04-15T00:00:00",
    "COD_ESTADO": "A",
    "FE_ULT_ACT": "2000-04-15T00:00:00"
  },
  {
    "COD_LOCALIDAD": 20456,
    "COD_POSTAL_VIEJO": 9408,
    "NOM_LOCALIDAD": "RIO TURBIO",
    "COD_IDENT_PROV": "Z",
    "FE_ALTA": "2004-02-15T01:39:32.302816",
    "COD_ESTADO": "A",
    "FE_ULT_ACT": "2004-02-15T01:39:32.302816"
  },
  {
    "COD_LOCALIDAD": 20457,
    "COD_POSTAL_VIEJO": 9398,
    "NOM_LOCALIDAD": "ROSPENTEK",
    "COD_IDENT_PROV": "Z",
    "FE_ALTA": "2004-02-15T01:39:32.302816",
    "COD_ESTADO": "A",
    "FE_ULT_ACT": "2004-02-15T01:39:32.302816"
  },
  {
    "COD_LOCALIDAD": 20457,
    "COD_POSTAL_VIEJO": 9407,
    "NOM_LOCALIDAD": "ROSPENTEK",
    "COD_IDENT_PROV": "Z",
    "FE_ALTA": "2000-04-15T00:00:00",
    "COD_ESTADO": "A",
    "FE_ULT_ACT": "2000-04-15T00:00:00"
  },
  {
    "COD_LOCALIDAD": 20457,
    "COD_POSTAL_VIEJO": 9408,
    "NOM_LOCALIDAD": "ROSPENTEK",
    "COD_IDENT_PROV": "Z",
    "FE_ALTA": "2004-02-15T01:39:32.302816",
    "COD_ESTADO": "A",
    "FE_ULT_ACT": "2004-02-15T01:39:32.302816"
  },
  {
    "COD_LOCALIDAD": 20458,
    "COD_POSTAL_VIEJO": 9398,
    "NOM_LOCALIDAD": "ROSPENTEK AIKE",
    "COD_IDENT_PROV": "Z",
    "FE_ALTA": "2004-02-15T01:39:32.302816",
    "COD_ESTADO": "A",
    "FE_ULT_ACT": "2004-02-15T01:39:32.302816"
  },
  {
    "COD_LOCALIDAD": 20458,
    "COD_POSTAL_VIEJO": 9407,
    "NOM_LOCALIDAD": "ROSPENTEK AIKE",
    "COD_IDENT_PROV": "Z",
    "FE_ALTA": "2000-04-15T00:00:00",
    "COD_ESTADO": "A",
    "FE_ULT_ACT": "2000-04-15T00:00:00"
  },
  {
    "COD_LOCALIDAD": 20458,
    "COD_POSTAL_VIEJO": 9408,
    "NOM_LOCALIDAD": "ROSPENTEK AIKE",
    "COD_IDENT_PROV": "Z",
    "FE_ALTA": "2004-02-15T01:39:32.302816",
    "COD_ESTADO": "A",
    "FE_ULT_ACT": "2004-02-15T01:39:32.302816"
  },
  {
    "COD_LOCALIDAD": 20459,
    "COD_POSTAL_VIEJO": 9051,
    "NOM_LOCALIDAD": "SARAI",
    "COD_IDENT_PROV": "Z",
    "FE_ALTA": "2000-04-15T00:00:00",
    "COD_ESTADO": "A",
    "FE_ULT_ACT": "2000-04-15T00:00:00"
  },
  {
    "COD_LOCALIDAD": 20460,
    "COD_POSTAL_VIEJO": 9303,
    "NOM_LOCALIDAD": "SIERRA DE LA VENTANA",
    "COD_IDENT_PROV": "Z",
    "FE_ALTA": "2000-04-15T00:00:00",
    "COD_ESTADO": "A",
    "FE_ULT_ACT": "2000-04-15T00:00:00"
  },
  {
    "COD_LOCALIDAD": 20461,
    "COD_POSTAL_VIEJO": 9315,
    "NOM_LOCALIDAD": "TAMEL AIKE",
    "COD_IDENT_PROV": "Z",
    "FE_ALTA": "2000-04-15T00:00:00",
    "COD_ESTADO": "A",
    "FE_ULT_ACT": "2000-04-15T00:00:00"
  },
  {
    "COD_LOCALIDAD": 20462,
    "COD_POSTAL_VIEJO": 9412,
    "NOM_LOCALIDAD": "TAPI AIKE",
    "COD_IDENT_PROV": "Z",
    "FE_ALTA": "2004-02-15T01:39:32.302816",
    "COD_ESTADO": "A",
    "FE_ULT_ACT": "2004-02-15T01:39:32.302816"
  },
  {
    "COD_LOCALIDAD": 20462,
    "COD_POSTAL_VIEJO": 9420,
    "NOM_LOCALIDAD": "TAPI AIKE",
    "COD_IDENT_PROV": "Z",
    "FE_ALTA": "2000-04-15T00:00:00",
    "COD_ESTADO": "A",
    "FE_ULT_ACT": "2000-04-15T00:00:00"
  },
  {
    "COD_LOCALIDAD": 20463,
    "COD_POSTAL_VIEJO": 9303,
    "NOM_LOCALIDAD": "TAUEL AIKE",
    "COD_IDENT_PROV": "Z",
    "FE_ALTA": "2000-04-15T00:00:00",
    "COD_ESTADO": "A",
    "FE_ULT_ACT": "2000-04-15T00:00:00"
  },
  {
    "COD_LOCALIDAD": 20464,
    "COD_POSTAL_VIEJO": 9018,
    "NOM_LOCALIDAD": "TEHUELCHES",
    "COD_IDENT_PROV": "Z",
    "FE_ALTA": "2004-02-15T01:39:32.302816",
    "COD_ESTADO": "A",
    "FE_ULT_ACT": "2004-02-15T01:39:32.302816"
  },
  {
    "COD_LOCALIDAD": 20464,
    "COD_POSTAL_VIEJO": 9019,
    "NOM_LOCALIDAD": "TEHUELCHES",
    "COD_IDENT_PROV": "Z",
    "FE_ALTA": "2000-04-15T00:00:00",
    "COD_ESTADO": "A",
    "FE_ULT_ACT": "2000-04-15T00:00:00"
  },
  {
    "COD_LOCALIDAD": 20465,
    "COD_POSTAL_VIEJO": 9050,
    "NOM_LOCALIDAD": "TELLIER",
    "COD_IDENT_PROV": "Z",
    "FE_ALTA": "2000-04-15T00:00:00",
    "COD_ESTADO": "A",
    "FE_ULT_ACT": "2000-04-15T00:00:00"
  },
  {
    "COD_LOCALIDAD": 20466,
    "COD_POSTAL_VIEJO": 9050,
    "NOM_LOCALIDAD": "TRES CERROS",
    "COD_IDENT_PROV": "Z",
    "FE_ALTA": "2000-04-15T00:00:00",
    "COD_ESTADO": "A",
    "FE_ULT_ACT": "2000-04-15T00:00:00"
  },
  {
    "COD_LOCALIDAD": 20467,
    "COD_POSTAL_VIEJO": 9301,
    "NOM_LOCALIDAD": "TRES LAGOS",
    "COD_IDENT_PROV": "Z",
    "FE_ALTA": "2000-04-15T00:00:00",
    "COD_ESTADO": "A",
    "FE_ULT_ACT": "2000-04-15T00:00:00"
  },
  {
    "COD_LOCALIDAD": 20468,
    "COD_POSTAL_VIEJO": 9051,
    "NOM_LOCALIDAD": "TRES PUNTAS",
    "COD_IDENT_PROV": "Z",
    "FE_ALTA": "2000-04-15T00:00:00",
    "COD_ESTADO": "A",
    "FE_ULT_ACT": "2000-04-15T00:00:00"
  },
  {
    "COD_LOCALIDAD": 20469,
    "COD_POSTAL_VIEJO": 9311,
    "NOM_LOCALIDAD": "TUCU TUCU",
    "COD_IDENT_PROV": "Z",
    "FE_ALTA": "2000-04-15T00:00:00",
    "COD_ESTADO": "A",
    "FE_ULT_ACT": "2000-04-15T00:00:00"
  },
  {
    "COD_LOCALIDAD": 20470,
    "COD_POSTAL_VIEJO": 9404,
    "NOM_LOCALIDAD": "VENTISQUERO MORENO",
    "COD_IDENT_PROV": "Z",
    "FE_ALTA": "2004-02-15T01:39:32.302816",
    "COD_ESTADO": "A",
    "FE_ULT_ACT": "2004-02-15T01:39:32.302816"
  },
  {
    "COD_LOCALIDAD": 20470,
    "COD_POSTAL_VIEJO": 9405,
    "NOM_LOCALIDAD": "VENTISQUERO MORENO",
    "COD_IDENT_PROV": "Z",
    "FE_ALTA": "2000-04-15T00:00:00",
    "COD_ESTADO": "A",
    "FE_ULT_ACT": "2000-04-15T00:00:00"
  },
  {
    "COD_LOCALIDAD": 20471,
    "COD_POSTAL_VIEJO": 9310,
    "NOM_LOCALIDAD": "YACIMIENTO CERRO VANGUARDIA",
    "COD_IDENT_PROV": "Z",
    "FE_ALTA": "2000-04-15T00:00:00",
    "COD_ESTADO": "A",
    "FE_ULT_ACT": "2000-04-15T00:00:00"
  },
  {
    "COD_LOCALIDAD": 20472,
    "COD_POSTAL_VIEJO": 9017,
    "NOM_LOCALIDAD": "YEGUA MUERTA",
    "COD_IDENT_PROV": "Z",
    "FE_ALTA": "2000-04-15T00:00:00",
    "COD_ESTADO": "A",
    "FE_ULT_ACT": "2000-04-15T00:00:00"
  },
  {
    "COD_LOCALIDAD": 20473,
    "COD_POSTAL_VIEJO": 9015,
    "NOM_LOCALIDAD": "ZANJON DEL PESCADO",
    "COD_IDENT_PROV": "Z",
    "FE_ALTA": "2000-04-15T00:00:00",
    "COD_ESTADO": "A",
    "FE_ULT_ACT": "2000-04-15T00:00:00"
  },
  {
    "COD_LOCALIDAD": 20474,
    "COD_POSTAL_VIEJO": 9398,
    "NOM_LOCALIDAD": "28 DE NOVIEMBRE",
    "COD_IDENT_PROV": "Z",
    "FE_ALTA": "2004-02-15T01:39:32.302816",
    "COD_ESTADO": "A",
    "FE_ULT_ACT": "2004-02-15T01:39:32.302816"
  },
  {
    "COD_LOCALIDAD": 20474,
    "COD_POSTAL_VIEJO": 9407,
    "NOM_LOCALIDAD": "28 DE NOVIEMBRE",
    "COD_IDENT_PROV": "Z",
    "FE_ALTA": "2000-04-15T00:00:00",
    "COD_ESTADO": "A",
    "FE_ULT_ACT": "2000-04-15T00:00:00"
  },
  {
    "COD_LOCALIDAD": 20474,
    "COD_POSTAL_VIEJO": 9408,
    "NOM_LOCALIDAD": "28 DE NOVIEMBRE",
    "COD_IDENT_PROV": "Z",
    "FE_ALTA": "2004-02-15T01:39:32.302816",
    "COD_ESTADO": "A",
    "FE_ULT_ACT": "2004-02-15T01:39:32.302816"
  }
]